{
  "slicer": "prusaslicer",
  "profile_type": "print",
  "name": "0.24 Standard @Snapmaker Artisan (0.8 nozzle)",
  "vendor": "Snapmaker",
  "first_seen": "3.0.0",
  "last_seen": "3.0.0",
  "filament_id": null,
  "setting_id": null,
  "renamed_from": null,
  "settings": {
    "adaptive_layer_height": {
      "3.0.0": "0"
    },
    "layer_height": {
      "3.0.0": "0.24"
    },
    "seam_position": {
      "3.0.0": "aligned"
    },
    "seam_gap": {
      "3.0.0": "15%"
    },
    "role_based_wipe_speed": {
      "3.0.0": "1"
    },
    "wipe_speed": {
      "3.0.0": "80%"
    },
    "wipe_on_loops": {
      "3.0.0": "1"
    },
    "slice_closing_radius": {
      "3.0.0": "0.049"
    },
    "resolution": {
      "3.0.0": "0.012"
    },
    "xy_contour_compensation": {
      "3.0.0": "0"
    },
    "elefant_foot_compensation": {
      "3.0.0": "0.1"
    },
    "precise_outer_wall": {
      "3.0.0": "1"
    },
    "ironing_spacing": {
      "3.0.0": "0.15"
    },
    "wall_transition_angle": {
      "3.0.0": "10"
    },
    "wall_transition_filter_deviation": {
      "3.0.0": "25%"
    },
    "wall_transition_length": {
      "3.0.0": "100%"
    },
    "wall_distribution_count": {
      "3.0.0": "1"
    },
    "min_bead_width": {
      "3.0.0": "85%"
    },
    "min_feature_size": {
      "3.0.0": "25%"
    },
    "bridge_density": {
      "3.0.0": "100%"
    },
    "thick_bridges": {
      "3.0.0": "1"
    },
    "top_solid_infill_flow_ratio": {
      "3.0.0": "1"
    },
    "bottom_solid_infill_flow_ratio": {
      "3.0.0": "1.2"
    },
    "only_one_wall_top": {
      "3.0.0": "0"
    },
    "only_one_wall_first_layer": {
      "3.0.0": "0"
    },
    "max_travel_detour_distance": {
      "3.0.0": "0"
    },
    "wipe_tower_no_sparse_layers": {
      "3.0.0": "0"
    },
    "draft_shield": {
      "3.0.0": "disabled"
    },
    "independent_support_layer_height": {
      "3.0.0": "1"
    },
    "interface_shells": {
      "3.0.0": "0"
    },
    "max_bridge_length": {
      "3.0.0": "10"
    },
    "print_flow_ratio": {
      "3.0.0": "1"
    },
    "top_surface_pattern": {
      "3.0.0": "monotonic"
    },
    "bottom_surface_pattern": {
      "3.0.0": "monotonic"
    },
    "filter_out_gap_fill": {
      "3.0.0": "0"
    },
    "infill_wall_overlap": {
      "3.0.0": "15%"
    },
    "infill_direction": {
      "3.0.0": "45"
    },
    "bridge_angle": {
      "3.0.0": "0"
    },
    "minimum_sparse_infill_area": {
      "3.0.0": "15"
    },
    "infill_combination": {
      "3.0.0": "0"
    },
    "detect_narrow_internal_solid_infill": {
      "3.0.0": "1"
    },
    "ensure_vertical_shell_thickness": {
      "3.0.0": "1"
    },
    "internal_bridge_support_thickness": {
      "3.0.0": "0.8"
    },
    "initial_layer_infill_speed": {
      "3.0.0": "75"
    },
    "initial_layer_travel_speed": {
      "3.0.0": "80%"
    },
    "ironing_speed": {
      "3.0.0": "35"
    },
    "overhang_speed_classic": {
      "3.0.0": "0"
    },
    "bridge_speed": {
      "3.0.0": "50"
    },
    "travel_speed": {
      "3.0.0": "190"
    },
    "default_acceleration": {
      "3.0.0": "2000"
    },
    "bridge_acceleration": {
      "3.0.0": "1000"
    },
    "travel_acceleration": {
      "3.0.0": "3000"
    },
    "default_jerk": {
      "3.0.0": "0"
    },
    "infill_jerk": {
      "3.0.0": "8"
    },
    "initial_layer_jerk": {
      "3.0.0": "8"
    },
    "inner_wall_jerk": {
      "3.0.0": "4"
    },
    "outer_wall_jerk": {
      "3.0.0": "4"
    },
    "top_surface_jerk": {
      "3.0.0": "4"
    },
    "travel_jerk": {
      "3.0.0": "10"
    },
    "support_type": {
      "3.0.0": "normal(auto)"
    },
    "support_critical_regions_only": {
      "3.0.0": "1"
    },
    "raft_layers": {
      "3.0.0": "0"
    },
    "raft_contact_distance": {
      "3.0.0": "0.1"
    },
    "raft_expansion": {
      "3.0.0": "2"
    },
    "raft_first_layer_density": {
      "3.0.0": "90%"
    },
    "tree_support_wall_count": {
      "3.0.0": "2"
    },
    "tree_support_adaptive_layer_height": {
      "3.0.0": "1"
    },
    "tree_support_auto_brim": {
      "3.0.0": "1"
    },
    "tree_support_brim_width": {
      "3.0.0": "3"
    },
    "tree_support_with_infill": {
      "3.0.0": "0"
    },
    "support_angle": {
      "3.0.0": "0"
    },
    "support_bottom_interface_spacing": {
      "3.0.0": "0.12"
    },
    "support_interface_loop_pattern": {
      "3.0.0": "0"
    },
    "support_expansion": {
      "3.0.0": "1"
    },
    "support_object_xy_distance": {
      "3.0.0": "0.9"
    },
    "skirt_distance": {
      "3.0.0": "2"
    },
    "skirt_height": {
      "3.0.0": "1"
    },
    "brim_type": {
      "3.0.0": "no_brim"
    },
    "brim_width": {
      "3.0.0": "5"
    },
    "prime_volume": {
      "3.0.0": "7.3"
    },
    "wipe_tower_cone_angle": {
      "3.0.0": "40"
    },
    "flush_into_infill": {
      "3.0.0": "0"
    },
    "flush_into_support": {
      "3.0.0": "1"
    },
    "flush_into_objects": {
      "3.0.0": "0"
    },
    "slicing_mode": {
      "3.0.0": "regular"
    },
    "print_sequence": {
      "3.0.0": "by layer"
    },
    "fuzzy_skin": {
      "3.0.0": "none"
    },
    "fuzzy_skin_thickness": {
      "3.0.0": "0.3"
    },
    "reduce_infill_retraction": {
      "3.0.0": "1"
    },
    "gcode_comments": {
      "3.0.0": "0"
    },
    "gcode_add_line_number": {
      "3.0.0": "0"
    },
    "gcode_label_objects": {
      "3.0.0": "1"
    },
    "post_process": {
      "3.0.0": ""
    },
    "enforce_support_layers": {
      "3.0.0": "0"
    },
    "exclude_object": {
      "3.0.0": "0"
    },
    "standby_temperature_delta": {
      "3.0.0": "-45"
    },
    "timelapse_type": {
      "3.0.0": "0"
    },
    "gap_fill_enabled": {
      "3.0.0": "0"
    },
    "single_extruder_multi_material_priming": {
      "3.0.0": "0"
    },
    "first_layer_height": {
      "3.0.0": "0.3"
    },
    "arc_fitting": {
      "3.0.0": "emit_center"
    },
    "perimeters": {
      "3.0.0": "2"
    },
    "top_solid_layers": {
      "3.0.0": "3"
    },
    "top_solid_min_thickness": {
      "3.0.0": "0.8"
    },
    "bottom_solid_layers": {
      "3.0.0": "3"
    },
    "bottom_solid_min_thickness": {
      "3.0.0": "0"
    },
    "avoid_crossing_perimeters": {
      "3.0.0": "1"
    },
    "overhangs": {
      "3.0.0": "1"
    },
    "perimeter_generator": {
      "3.0.0": "arachne"
    },
    "fill_density": {
      "3.0.0": "15%"
    },
    "fill_pattern": {
      "3.0.0": "cubic"
    },
    "extrusion_width": {
      "3.0.0": "0.82"
    },
    "first_layer_extrusion_width": {
      "3.0.0": "0.82"
    },
    "perimeter_extrusion_width": {
      "3.0.0": "0.82"
    },
    "external_perimeter_extrusion_width": {
      "3.0.0": "0.82"
    },
    "top_infill_extrusion_width": {
      "3.0.0": "0.82"
    },
    "infill_extrusion_width": {
      "3.0.0": "0.82"
    },
    "solid_infill_extrusion_width": {
      "3.0.0": "0.82"
    },
    "support_material_extrusion_width": {
      "3.0.0": "0.82"
    },
    "xy_size_compensation": {
      "3.0.0": "0"
    },
    "ironing_flowrate": {
      "3.0.0": "10%"
    },
    "bridge_flow_ratio": {
      "3.0.0": "0.95"
    },
    "thin_walls": {
      "3.0.0": "0"
    },
    "first_layer_speed": {
      "3.0.0": "50"
    },
    "external_perimeter_speed": {
      "3.0.0": "145"
    },
    "perimeter_speed": {
      "3.0.0": "160"
    },
    "infill_speed": {
      "3.0.0": "160"
    },
    "solid_infill_speed": {
      "3.0.0": "160"
    },
    "top_solid_infill_speed": {
      "3.0.0": "100"
    },
    "gap_fill_speed": {
      "3.0.0": "160"
    },
    "support_material_speed": {
      "3.0.0": "100"
    },
    "support_material_interface_speed": {
      "3.0.0": "50"
    },
    "enable_dynamic_overhang_speeds": {
      "3.0.0": "1"
    },
    "overhang_speed_3": {
      "3.0.0": "0"
    },
    "overhang_speed_2": {
      "3.0.0": "25"
    },
    "overhang_speed_1": {
      "3.0.0": "15"
    },
    "overhang_speed_0": {
      "3.0.0": "10"
    },
    "external_perimeter_acceleration": {
      "3.0.0": "1000"
    },
    "perimeter_acceleration": {
      "3.0.0": "2000"
    },
    "infill_acceleration": {
      "3.0.0": "2000"
    },
    "solid_infill_acceleration": {
      "3.0.0": "2000"
    },
    "first_layer_acceleration": {
      "3.0.0": "500"
    },
    "top_solid_infill_acceleration": {
      "3.0.0": "1000"
    },
    "support_material": {
      "3.0.0": "0"
    },
    "support_material_style": {
      "3.0.0": "snug"
    },
    "support_material_buildplate_only": {
      "3.0.0": "1"
    },
    "support_material_extruder": {
      "3.0.0": "1"
    },
    "support_material_interface_extruder": {
      "3.0.0": "2"
    },
    "support_material_contact_distance": {
      "3.0.0": "0"
    },
    "support_material_bottom_contact_distance": {
      "3.0.0": "0"
    },
    "support_material_pattern": {
      "3.0.0": "rectilinear"
    },
    "support_material_spacing": {
      "3.0.0": "2.5"
    },
    "support_material_threshold": {
      "3.0.0": "30"
    },
    "support_material_interface_layers": {
      "3.0.0": "3"
    },
    "support_material_bottom_interface_layers": {
      "3.0.0": "3"
    },
    "support_material_interface_pattern": {
      "3.0.0": "rectilinear"
    },
    "support_material_interface_spacing": {
      "3.0.0": "0.12"
    },
    "support_tree_branch_distance": {
      "3.0.0": "5"
    },
    "support_tree_branch_diameter": {
      "3.0.0": "5"
    },
    "support_tree_branch_diameter_angle": {
      "3.0.0": "15"
    },
    "dont_support_bridges": {
      "3.0.0": "1"
    },
    "skirts": {
      "3.0.0": "0"
    },
    "brim_separation": {
      "3.0.0": "0"
    },
    "wipe_tower": {
      "3.0.0": "1"
    },
    "wipe_tower_width": {
      "3.0.0": "25"
    },
    "wipe_tower_brim_width": {
      "3.0.0": "5"
    },
    "spiral_vase": {
      "3.0.0": "0"
    },
    "fuzzy_skin_point_dist": {
      "3.0.0": "0.8"
    },
    "output_filename_format": {
      "3.0.0": "{input_filename_base}_{layer_height}mm_{print_time}.gcode"
    },
    "small_perimeter_threshold": {
      "3.0.0": "0"
    },
    "support_material_synchronize_layers": {
      "3.0.0": "1"
    },
    "compatible_printers_condition": {
      "3.0.0": "(printer_model==\"Snapmaker Artisan\") and (nozzle_diameter[0]==\"0.8\")"
    },
    "print_settings_id": {
      "3.0.0": "0.24 Standard @Snapmaker Artisan (0.8 nozzle)"
    }
  }
}