{
  "slicer": "prusaslicer",
  "profile_type": "machine_model",
  "name": "VORON Trident 300mm",
  "vendor": "Voron",
  "first_seen": "3.0.0",
  "last_seen": "3.0.0",
  "filament_id": null,
  "setting_id": null,
  "renamed_from": null,
  "settings": {
    "name": {
      "3.0.0": "VORON Trident 300mm"
    },
    "variants": {
      "3.0.0": "HF0.4; HF0.5; HF0.6; HF0.8; 0.25; 0.3; 0.4; 0.5; 0.6; 0.8"
    },
    "technology": {
      "3.0.0": "FFF"
    },
    "family": {
      "3.0.0": "VORON Trident"
    },
    "bed_model": {
      "3.0.0": "sha256:3ca72664a3cbfd50929305774c860f6ac87ab03a7b661dc265ccc3da72f3db00"
    },
    "bed_texture": {
      "3.0.0": "sha256:643256b1361a8eb9d10e81b8ed270eb81ba7752561a7a2eb8ec65f66543c8d4e"
    },
    "thumbnail": {
      "3.0.0": "sha256:a2559bea2d1fa37c0a2976a4a32bdf5dca0288bc73ad83a8a39a53ee96de4a8c"
    },
    "default_materials": {
      "3.0.0": "Generic ABS @Voron HF0.4; Generic ASA @Voron HF0.4; Generic PLA @Voron HF0.4; Generic PETG @Voron HF0.4"
    }
  }
}