{
  "slicer": "kirimoto",
  "profile_type": "filament",
  "name": "Tina2 PLA Profile",
  "vendor": "Tina2",
  "first_seen": "4.7.1",
  "last_seen": "4.7.1",
  "filament_id": null,
  "setting_id": null,
  "renamed_from": null,
  "filament_type": "PLA",
  "native_id": "Tina2.Basic:filament:0",
  "context": {
    "printer_model": "Tina2 Basic"
  },
  "setting_scopes": {},
  "settings": {
    "outputTemp": {
      "4.7.1": 200
    },
    "outputBedTemp": {
      "4.7.1": 0
    },
    "type": {
      "4.7.1": "filament"
    },
    "name": {
      "4.7.1": "Tina2 PLA Profile"
    },
    "filament_type": {
      "4.7.1": "PLA"
    },
    "compatible_printers": {
      "4.7.1": [
        "Tina2 Basic 0.4 nozzle"
      ]
    }
  }
}