{
  "slicer": "cura",
  "profile_type": "print",
  "name": "Draft · @ultimaker_sketch_sprint · 0.4mm · ultimaker_tough_pla_175 · quick",
  "vendor": "Ultimaker B.V.",
  "first_seen": "5.13.0",
  "last_seen": "5.13.0",
  "filament_id": null,
  "setting_id": "intent:ultimaker_sketch_sprint:ultimaker_sketch_sprint/um_sketch_sprint_0.4mm_um-tough-pla-175_0.27mm_draft",
  "renamed_from": null,
  "filament_type": null,
  "native_id": "intent:ultimaker_sketch_sprint:ultimaker_sketch_sprint/um_sketch_sprint_0.4mm_um-tough-pla-175_0.27mm_draft",
  "context": {
    "native_id": "intent:ultimaker_sketch_sprint:ultimaker_sketch_sprint/um_sketch_sprint_0.4mm_um-tough-pla-175_0.27mm_draft",
    "source_kind": "intent",
    "resource_version": "5.13.0",
    "definition": "ultimaker_sketch_sprint",
    "quality_type": "imperial",
    "intent_category": "quick",
    "variant_name": "0.4mm",
    "material_id": "ultimaker_tough_pla_175",
    "global_quality_id": null,
    "compatibility": {
      "machine_definition_ids": [
        "ultimaker_sketch_sprint"
      ],
      "variant_names": [
        "0.4mm"
      ],
      "material_native_ids": [
        "ultimaker_tough_pla_175"
      ]
    }
  },
  "setting_scopes": {
    "speed_print": "extruder.0",
    "support_line_width": "extruder.0",
    "infill_angles": "extruder.0",
    "infill_overlap": "extruder.0",
    "acceleration_topbottom": "extruder.0",
    "acceleration_layer_0": "extruder.0",
    "initial_layer_line_width_factor": "extruder.0",
    "acceleration_wall_x_roofing": "extruder.0",
    "infill_pattern": "extruder.0",
    "cool_min_speed": "extruder.0",
    "speed_wall_x_roofing": "extruder.0",
    "material_initial_print_temperature": "extruder.0",
    "acceleration_print": "extruder.0",
    "seam_overhang_angle": "extruder.0",
    "acceleration_roofing": "extruder.0",
    "retraction_hop_enabled": "extruder.0",
    "cool_min_layer_time": "extruder.0",
    "material_print_temperature": "extruder.0",
    "wall_overhang_angle": "extruder.0",
    "acceleration_wall_x": "extruder.0",
    "speed_roofing": "extruder.0",
    "infill_wipe_dist": "extruder.0",
    "speed_support_interface": "extruder.0",
    "speed_wall": "extruder.0",
    "speed_support_bottom": "extruder.0",
    "cool_min_temperature": "extruder.0",
    "infill_line_width": "extruder.0",
    "speed_wall_x": "extruder.0",
    "material_final_print_temperature": "extruder.0",
    "speed_layer_0": "extruder.0",
    "acceleration_wall_0_roofing": "extruder.0",
    "line_width": "extruder.0",
    "wall_line_width_x": "extruder.0",
    "speed_topbottom": "extruder.0",
    "acceleration_wall_0": "extruder.0",
    "wall_overhang_speed_factors": "extruder.0",
    "cool_fan_full_at_height": "extruder.0",
    "acceleration_travel_layer_0": "extruder.0"
  },
  "settings": {
    "speed_print": {
      "5.13.0": 270
    },
    "support_line_width": {
      "5.13.0": 0.35
    },
    "infill_angles": {
      "5.13.0": [
        135
      ]
    },
    "infill_overlap": {
      "5.13.0": 25
    },
    "acceleration_topbottom": {
      "5.13.0": 10000
    },
    "acceleration_layer_0": {
      "5.13.0": 5000
    },
    "initial_layer_line_width_factor": {
      "5.13.0": 125
    },
    "acceleration_wall_x_roofing": {
      "5.13.0": 5000
    },
    "infill_pattern": {
      "5.13.0": "zigzag"
    },
    "cool_min_speed": {
      "5.13.0": 50
    },
    "speed_wall_x_roofing": {
      "5.13.0": 270
    },
    "material_initial_print_temperature": {
      "5.13.0": 225
    },
    "acceleration_print": {
      "5.13.0": 20000
    },
    "seam_overhang_angle": {
      "5.13.0": 25
    },
    "acceleration_roofing": {
      "5.13.0": 5000
    },
    "retraction_hop_enabled": {
      "5.13.0": true
    },
    "cool_min_layer_time": {
      "5.13.0": 2
    },
    "material_print_temperature": {
      "5.13.0": 225
    },
    "wall_overhang_angle": {
      "5.13.0": 25
    },
    "acceleration_wall_x": {
      "5.13.0": 10000
    },
    "speed_roofing": {
      "5.13.0": 215
    },
    "infill_wipe_dist": {
      "5.13.0": 0.05
    },
    "speed_support_interface": {
      "5.13.0": 215
    },
    "speed_wall": {
      "5.13.0": 215
    },
    "speed_support_bottom": {
      "5.13.0": 100
    },
    "cool_min_temperature": {
      "5.13.0": 220
    },
    "infill_line_width": {
      "5.13.0": 0.4
    },
    "speed_wall_x": {
      "5.13.0": 270
    },
    "material_final_print_temperature": {
      "5.13.0": 225
    },
    "speed_layer_0": {
      "5.13.0": 70
    },
    "acceleration_wall_0_roofing": {
      "5.13.0": 5000
    },
    "line_width": {
      "5.13.0": 0.4
    },
    "wall_line_width_x": {
      "5.13.0": 0.4
    },
    "speed_topbottom": {
      "5.13.0": 215
    },
    "acceleration_wall_0": {
      "5.13.0": 5000.0
    },
    "wall_overhang_speed_factors": {
      "5.13.0": [
        15
      ]
    },
    "cool_fan_full_at_height": {
      "5.13.0": 0.54
    },
    "acceleration_travel_layer_0": {
      "5.13.0": 5000
    }
  }
}