{
  "slicer": "cura",
  "profile_type": "print",
  "name": "Fast · @ultimaker_factor4 · BB 0.4 · generic_pva",
  "vendor": "Ultimaker B.V.",
  "first_seen": "5.13.0",
  "last_seen": "5.13.0",
  "filament_id": null,
  "setting_id": "quality:ultimaker_factor4:ultimaker_factor4/um_f4_bb0.4_pva_0.2mm",
  "renamed_from": null,
  "filament_type": null,
  "native_id": "quality:ultimaker_factor4:ultimaker_factor4/um_f4_bb0.4_pva_0.2mm",
  "context": {
    "native_id": "quality:ultimaker_factor4:ultimaker_factor4/um_f4_bb0.4_pva_0.2mm",
    "source_kind": "quality",
    "resource_version": "5.13.0",
    "definition": "ultimaker_factor4",
    "quality_type": "draft",
    "intent_category": null,
    "variant_name": "BB 0.4",
    "material_id": "generic_pva",
    "global_quality_id": "quality:ultimaker_factor4:ultimaker_factor4/um_f4_global_Draft_Quality",
    "compatibility": {
      "machine_definition_ids": [
        "ultimaker_factor4"
      ],
      "variant_names": [
        "BB 0.4"
      ],
      "material_native_ids": [
        "generic_pva"
      ]
    }
  },
  "setting_scopes": {
    "support_infill_sparse_thickness": "extruder.0",
    "speed_print": "extruder.0",
    "retraction_prime_speed": "extruder.0",
    "acceleration_support_interface": "extruder.0",
    "build_volume_temperature": "global",
    "gradual_flow_discretisation_step_size": "extruder.0",
    "minimum_support_area": "extruder.0",
    "default_material_bed_temperature": "global",
    "initial_layer_line_width_factor": "extruder.0",
    "support_angle": "extruder.0",
    "jerk_print": "extruder.0",
    "support_infill_rate": "extruder.0",
    "acceleration_print": "extruder.0",
    "acceleration_support_bottom": "extruder.0",
    "material_flow_layer_0": "extruder.0",
    "support_z_distance": "extruder.0",
    "support_interface_offset": "extruder.0",
    "switch_extruder_prime_speed": "extruder.0",
    "layer_height": "global",
    "support_offset": "extruder.0",
    "prime_tower_flow": "extruder.0",
    "max_flow_acceleration": "extruder.0",
    "gradual_flow_enabled": "extruder.0",
    "prime_tower_min_volume": "extruder.0",
    "support_xy_distance": "extruder.0",
    "skin_material_flow": "extruder.0",
    "gradual_support_infill_steps": "extruder.0",
    "brim_replaces_support": "extruder.0",
    "retraction_min_travel": "extruder.0"
  },
  "settings": {
    "support_infill_sparse_thickness": {
      "5.13.0": 0.2
    },
    "speed_print": {
      "5.13.0": 30
    },
    "retraction_prime_speed": {
      "5.13.0": 10.0
    },
    "acceleration_support_interface": {
      "5.13.0": 1000
    },
    "build_volume_temperature": {
      "5.13.0": 40
    },
    "gradual_flow_discretisation_step_size": {
      "5.13.0": 0.1
    },
    "minimum_support_area": {
      "5.13.0": 4
    },
    "default_material_bed_temperature": {
      "5.13.0": 0
    },
    "initial_layer_line_width_factor": {
      "5.13.0": 125
    },
    "support_angle": {
      "5.13.0": 45
    },
    "jerk_print": {
      "5.13.0": 10
    },
    "support_infill_rate": {
      "5.13.0": 20
    },
    "acceleration_print": {
      "5.13.0": 1000.0
    },
    "acceleration_support_bottom": {
      "5.13.0": 100
    },
    "material_flow_layer_0": {
      "5.13.0": 90
    },
    "support_z_distance": {
      "5.13.0": 0
    },
    "support_interface_offset": {
      "5.13.0": 1
    },
    "switch_extruder_prime_speed": {
      "5.13.0": 10.0
    },
    "layer_height": {
      "5.13.0": 0.2
    },
    "support_offset": {
      "5.13.0": 3
    },
    "prime_tower_flow": {
      "5.13.0": 90
    },
    "max_flow_acceleration": {
      "5.13.0": 1
    },
    "gradual_flow_enabled": {
      "5.13.0": true
    },
    "prime_tower_min_volume": {
      "5.13.0": 15
    },
    "support_xy_distance": {
      "5.13.0": 2
    },
    "skin_material_flow": {
      "5.13.0": 93.0
    },
    "gradual_support_infill_steps": {
      "5.13.0": 0
    },
    "brim_replaces_support": {
      "5.13.0": false
    },
    "retraction_min_travel": {
      "5.13.0": 5.0
    }
  }
}