[
    {
        "compatible_printers": {
            "Geeetech A20 T": [
                "0.4"
            ]
        },
        "data": {
            "bed_temperature": "70",
            "bridge_fan_speed": "100",
            "compatible_printers_condition": "printer_notes=~/.*PRINTER_VENDOR_Geeetech.*/ and printer_model=~/(M1|Thunder|ThunderPro|Mizar|A10|A20|A30).*/",
            "cooling": "1",
            "disable_fan_first_layers": "3",
            "extrusion_multiplier": "1",
            "fan_always_on": "1",
            "fan_below_layer_time": "20",
            "filament_colour": "#42BDD8",
            "filament_cost": "30",
            "filament_density": "1.27",
            "filament_diameter": "1.75",
            "filament_max_volumetric_speed": "0",
            "filament_minimal_purge_on_wipe_tower": "90",
            "filament_notes": "\"\"",
            "filament_settings_id": "Geeetech PETG @Geeetech",
            "filament_soluble": "0",
            "filament_type": "PETG",
            "filament_vendor": "Geeetech",
            "first_layer_bed_temperature": "70",
            "first_layer_temperature": "240",
            "max_fan_speed": "40",
            "min_fan_speed": "20",
            "min_print_speed": "15",
            "slowdown_below_layer_time": "20",
            "temperature": "240"
        },
        "filament_db_ids": [
            "geeetech/PETG/petg"
        ],
        "name": "Geeetech PETG @Geeetech"
    },
    {
        "compatible_printers": {
            "Geeetech A20 T": [
                "0.4"
            ]
        },
        "data": {
            "bed_temperature": "60",
            "bridge_fan_speed": "100",
            "compatible_printers_condition": "printer_notes=~/.*PRINTER_VENDOR_Geeetech.*/ and printer_model=~/(M1|Thunder|ThunderPro|Mizar|A10|A20|A30).*/",
            "cooling": "1",
            "disable_fan_first_layers": "2",
            "extrusion_multiplier": "1",
            "fan_always_on": "1",
            "fan_below_layer_time": "100",
            "filament_colour": "#DDDDDD",
            "filament_cost": "25.4",
            "filament_density": "1.24",
            "filament_diameter": "1.75",
            "filament_max_volumetric_speed": "0",
            "filament_minimal_purge_on_wipe_tower": "90",
            "filament_notes": "\"\"",
            "filament_settings_id": "Generic PLA @Geeetech",
            "filament_soluble": "0",
            "filament_type": "PLA",
            "filament_vendor": "Generic",
            "first_layer_bed_temperature": "60",
            "first_layer_temperature": "210",
            "max_fan_speed": "100",
            "min_fan_speed": "100",
            "min_print_speed": "15",
            "slowdown_below_layer_time": "20",
            "temperature": "205"
        },
        "name": "Generic PLA @Geeetech"
    },
    {
        "compatible_printers": {
            "Geeetech A20 T": [
                "0.4"
            ]
        },
        "data": {
            "bed_temperature": "70",
            "bridge_fan_speed": "100",
            "compatible_printers_condition": "printer_notes=~/.*PRINTER_VENDOR_Geeetech.*/ and printer_model=~/(M1|Thunder|ThunderPro|Mizar|A10|A20|A30).*/",
            "cooling": "1",
            "disable_fan_first_layers": "3",
            "extrusion_multiplier": "1",
            "fan_always_on": "1",
            "fan_below_layer_time": "20",
            "filament_colour": "#DDDDDD",
            "filament_cost": "27.82",
            "filament_density": "1.27",
            "filament_diameter": "1.75",
            "filament_max_volumetric_speed": "0",
            "filament_minimal_purge_on_wipe_tower": "90",
            "filament_notes": "\"\"",
            "filament_settings_id": "Generic PETG @Geeetech",
            "filament_soluble": "0",
            "filament_type": "PETG",
            "filament_vendor": "Generic",
            "first_layer_bed_temperature": "70",
            "first_layer_temperature": "240",
            "max_fan_speed": "50",
            "min_fan_speed": "20",
            "min_print_speed": "15",
            "slowdown_below_layer_time": "20",
            "temperature": "240"
        },
        "name": "Generic PETG @Geeetech"
    },
    {
        "compatible_printers": {
            "Geeetech A20 T": [
                "0.4"
            ]
        },
        "data": {
            "bed_temperature": "100",
            "bridge_fan_speed": "30",
            "compatible_printers_condition": "printer_notes=~/.*PRINTER_VENDOR_Geeetech.*/ and printer_model=~/(Thunder|ThunderPro|Mizar|A10|A20|A30).*/",
            "cooling": "0",
            "disable_fan_first_layers": "3",
            "extrusion_multiplier": "1",
            "fan_always_on": "0",
            "fan_below_layer_time": "20",
            "filament_colour": "#DDDDDD",
            "filament_cost": "27.82",
            "filament_density": "1.04",
            "filament_diameter": "1.75",
            "filament_max_volumetric_speed": "0",
            "filament_minimal_purge_on_wipe_tower": "90",
            "filament_notes": "\"\"",
            "filament_settings_id": "Generic ABS @Geeetech",
            "filament_soluble": "0",
            "filament_type": "ABS",
            "filament_vendor": "Generic",
            "first_layer_bed_temperature": "100",
            "first_layer_temperature": "245",
            "max_fan_speed": "0",
            "min_fan_speed": "0",
            "min_print_speed": "15",
            "slowdown_below_layer_time": "20",
            "temperature": "245",
            "top_fan_speed": "0"
        },
        "name": "Generic ABS @Geeetech"
    },
    {
        "compatible_printers": {
            "Geeetech A20 T": [
                "0.4"
            ]
        },
        "data": {
            "bed_temperature": "55",
            "compatible_printers_condition": "printer_notes=~/.*PRINTER_VENDOR_Geeetech.*/ and printer_model=~/(M1|Thunder|ThunderPro|Mizar|A10|A20|A30).*/",
            "cooling": "0",
            "disable_fan_first_layers": "3",
            "extrusion_multiplier": "1",
            "fan_always_on": "0",
            "fan_below_layer_time": "20",
            "filament_colour": "#CFFFFB",
            "filament_cost": "30",
            "filament_density": "1.2",
            "filament_diameter": "1.75",
            "filament_max_volumetric_speed": "0",
            "filament_minimal_purge_on_wipe_tower": "90",
            "filament_notes": "\"\"",
            "filament_retract_before_travel": "4",
            "filament_retract_length": "2.5",
            "filament_retract_speed": "30",
            "filament_settings_id": "Generic TPU @Geeetech",
            "filament_soluble": "0",
            "filament_type": "TPU",
            "filament_vendor": "Geeetech",
            "first_layer_bed_temperature": "55",
            "first_layer_temperature": "210",
            "max_fan_speed": "70",
            "min_fan_speed": "0",
            "min_print_speed": "15",
            "slowdown_below_layer_time": "20"
        },
        "name": "Generic TPU @Geeetech"
    },
    {
        "compatible_printers": {
            "Geeetech A20 T": [
                "0.4"
            ]
        },
        "data": {
            "bed_temperature": "60",
            "bridge_fan_speed": "100",
            "compatible_printers_condition": "printer_notes=~/.*PRINTER_VENDOR_Geeetech.*/ and printer_model=~/(M1|Thunder|ThunderPro|Mizar|A10|A20|A30).*/",
            "cooling": "1",
            "disable_fan_first_layers": "2",
            "extrusion_multiplier": "1",
            "fan_always_on": "1",
            "fan_below_layer_time": "100",
            "filament_colour": "#42BDD8",
            "filament_cost": "20",
            "filament_density": "1.24",
            "filament_diameter": "1.75",
            "filament_max_volumetric_speed": "0",
            "filament_minimal_purge_on_wipe_tower": "90",
            "filament_notes": "\"\"",
            "filament_settings_id": "Geeetech PLA @Geeetech",
            "filament_soluble": "0",
            "filament_type": "PLA",
            "filament_vendor": "Geeetech",
            "first_layer_bed_temperature": "60",
            "first_layer_temperature": "205",
            "max_fan_speed": "100",
            "min_fan_speed": "100",
            "min_print_speed": "15",
            "slowdown_below_layer_time": "20",
            "temperature": "200"
        },
        "filament_db_ids": [
            "geeetech/PLA/pla"
        ],
        "name": "Geeetech PLA @Geeetech"
    }
]