{
  "slicer": "orcaslicer",
  "profile_type": "filament",
  "name": "Soleyin Basic PETG @Hi-all",
  "vendor": "Creality",
  "first_seen": "2.4.0",
  "last_seen": "2.4.1",
  "filament_id": "06005",
  "setting_id": "GFSA04",
  "renamed_from": null,
  "settings": {
    "type": {
      "2.4.0": "filament"
    },
    "name": {
      "2.4.0": "Soleyin Basic PETG @Hi-all"
    },
    "instantiation": {
      "2.4.0": "true"
    },
    "close_fan_the_first_x_layers": {
      "2.4.0": [
        "3"
      ]
    },
    "cool_plate_temp": {
      "2.4.0": [
        "80"
      ]
    },
    "cool_plate_temp_initial_layer": {
      "2.4.0": [
        "80"
      ]
    },
    "eng_plate_temp": {
      "2.4.0": [
        "80"
      ]
    },
    "eng_plate_temp_initial_layer": {
      "2.4.0": [
        "80"
      ]
    },
    "fan_cooling_layer_time": {
      "2.4.0": [
        "30"
      ]
    },
    "fan_max_speed": {
      "2.4.0": [
        "80"
      ]
    },
    "fan_min_speed": {
      "2.4.0": [
        "60"
      ]
    },
    "filament_cost": {
      "2.4.0": [
        "15.9"
      ]
    },
    "filament_density": {
      "2.4.0": [
        "1.25"
      ]
    },
    "filament_deretraction_speed": {
      "2.4.0": [
        "30"
      ]
    },
    "filament_diameter": {
      "2.4.0": [
        "1.75"
      ]
    },
    "filament_flow_ratio": {
      "2.4.0": [
        "0.96"
      ]
    },
    "filament_max_volumetric_speed": {
      "2.4.0": [
        "16"
      ]
    },
    "filament_minimal_purge_on_wipe_tower": {
      "2.4.0": [
        "15"
      ]
    },
    "filament_retract_before_wipe": {
      "2.4.0": [
        "90%"
      ]
    },
    "filament_retract_restart_extra": {
      "2.4.0": [
        "nil"
      ]
    },
    "filament_retract_when_changing_layer": {
      "2.4.0": [
        "nil"
      ]
    },
    "filament_retraction_length": {
      "2.4.0": [
        "0.4"
      ]
    },
    "filament_retraction_minimum_travel": {
      "2.4.0": [
        "2"
      ]
    },
    "filament_retraction_speed": {
      "2.4.0": [
        "30"
      ]
    },
    "filament_settings_id": {
      "2.4.0": [
        ""
      ]
    },
    "filament_soluble": {
      "2.4.0": [
        "0"
      ]
    },
    "filament_type": {
      "2.4.0": [
        "PETG"
      ]
    },
    "filament_vendor": {
      "2.4.0": [
        "Creality"
      ]
    },
    "filament_wipe": {
      "2.4.0": [
        "nil"
      ]
    },
    "filament_wipe_distance": {
      "2.4.0": [
        "2"
      ]
    },
    "filament_z_hop": {
      "2.4.0": [
        "nil"
      ]
    },
    "filament_z_hop_types": {
      "2.4.0": [
        "Slope Lift"
      ]
    },
    "full_fan_speed_layer": {
      "2.4.0": [
        "0"
      ]
    },
    "hot_plate_temp": {
      "2.4.0": [
        "80"
      ]
    },
    "hot_plate_temp_initial_layer": {
      "2.4.0": [
        "80"
      ]
    },
    "nozzle_temperature": {
      "2.4.0": [
        "250"
      ]
    },
    "nozzle_temperature_initial_layer": {
      "2.4.0": [
        "250"
      ]
    },
    "overhang_fan_speed": {
      "2.4.0": [
        "100"
      ]
    },
    "overhang_fan_threshold": {
      "2.4.0": [
        "25%"
      ]
    },
    "reduce_fan_stop_start_freq": {
      "2.4.0": [
        "1"
      ]
    },
    "slow_down_for_layer_cooling": {
      "2.4.0": [
        "1"
      ]
    },
    "slow_down_layer_time": {
      "2.4.0": [
        "12"
      ]
    },
    "slow_down_min_speed": {
      "2.4.0": [
        "20"
      ]
    },
    "temperature_vitrification": {
      "2.4.0": [
        "100"
      ]
    },
    "textured_plate_temp": {
      "2.4.0": [
        "80"
      ]
    },
    "textured_plate_temp_initial_layer": {
      "2.4.0": [
        "80"
      ]
    },
    "filament_start_gcode": {
      "2.4.0": [
        "; Filament gcode\n"
      ]
    },
    "filament_end_gcode": {
      "2.4.0": [
        "; filament end gcode \n"
      ]
    },
    "from": {
      "2.4.0": "system"
    },
    "filament_adhesiveness_category": {
      "2.4.0": [
        "300"
      ]
    },
    "bed_type": {
      "2.4.0": [
        "Cool Plate"
      ]
    },
    "setting_id": {
      "2.4.0": "GFSA04",
      "2.4.1": "sUalM5HH0sDpMOmD"
    },
    "complete_print_exhaust_fan_speed": {
      "2.4.0": [
        "0"
      ]
    },
    "during_print_exhaust_fan_speed": {
      "2.4.0": [
        "0"
      ]
    },
    "nozzle_temperature_range_high": {
      "2.4.0": [
        "270"
      ]
    },
    "nozzle_temperature_range_low": {
      "2.4.0": [
        "220"
      ]
    },
    "customized_plate_temp": {
      "2.4.0": "80"
    },
    "customized_plate_temp_initial_layer": {
      "2.4.0": "80"
    },
    "enable_pressure_advance": {
      "2.4.0": "0"
    },
    "epoxy_resin_plate_temp": {
      "2.4.0": "70"
    },
    "epoxy_resin_plate_temp_initial_layer": {
      "2.4.0": "70"
    },
    "filament_retract_lift_above": {
      "2.4.0": "nil"
    },
    "filament_retract_lift_below": {
      "2.4.0": "nil"
    },
    "filament_retract_lift_enforce": {
      "2.4.0": "nil"
    },
    "material_flow_temp_graph": {
      "2.4.0": "[[0.6,220],[1.4,220],[1.7,250]]"
    },
    "pressure_advance": {
      "2.4.0": "0.06"
    },
    "default_filament_colour": {
      "2.4.0": "\"\""
    },
    "compatible_printers": {
      "2.4.0": [
        "Creality Hi 0.4 nozzle",
        "Creality Hi 0.6 nozzle",
        "Creality Hi 0.8 nozzle"
      ]
    },
    "filament_id": {
      "2.4.0": "06005"
    }
  }
}