{
  "slicer": "cura",
  "profile_type": "filament",
  "name": "Vertex Delta ABS",
  "vendor": "Velleman",
  "first_seen": "2026-02-25",
  "last_seen": "2026-02-25",
  "filament_id": "4edd8fce-0851-43e5-808a-970b4bfe8b10",
  "setting_id": null,
  "renamed_from": null,
  "settings": {
    "brand": {
      "2026-02-25": "Velleman"
    },
    "material": {
      "2026-02-25": "ABS"
    },
    "color": {
      "2026-02-25": "Generic"
    },
    "label": {
      "2026-02-25": "Vertex Delta ABS"
    },
    "GUID": {
      "2026-02-25": "4edd8fce-0851-43e5-808a-970b4bfe8b10"
    },
    "color_code": {
      "2026-02-25": "#ffc924"
    },
    "description": {
      "2026-02-25": ""
    },
    "diameter": {
      "2026-02-25": "1.75"
    },
    "density": {
      "2026-02-25": "1.24"
    },
    "weight": {
      "2026-02-25": ""
    },
    "standby temperature": {
      "2026-02-25": "225.0"
    },
    "print cooling": {
      "2026-02-25": "0.0"
    },
    "retraction amount": {
      "2026-02-25": "3.0"
    },
    "print temperature": {
      "2026-02-25": "250.0"
    },
    "heated bed temperature": {
      "2026-02-25": "0.0"
    },
    "retraction speed": {
      "2026-02-25": "150.0"
    },
    "build volume temperature": {
      "2026-02-25": "36"
    }
  }
}