{
    "1": {
        "prusaslicer": [
            "Creality/Creality CR-10 S"
        ],
        "superslicer": [
            "Creality/Creality CR-10 S"
        ],
        "cura": [
            "Creality3D/Creality CR-10S"
        ]
    },
    "4": {
        "prusaslicer": [
            "Creality/Creality Ender-5"
        ],
        "orcaslicer": [
            "Creality/Creality Ender-5"
        ],
        "bambustudio": [
            "Creality/Creality Ender-5"
        ],
        "elegooslicer": [
            "Creality/Creality Ender-5"
        ],
        "superslicer": [
            "Creality/Creality Ender-5"
        ],
        "cura": [
            "Creality3D/Creality Ender-5"
        ]
    },
    "5": {
        "prusaslicer": [
            "Creality/Creality CR-10"
        ],
        "superslicer": [
            "Creality/Creality CR-10"
        ],
        "cura": [
            "Creality3D/Creality CR-10"
        ]
    },
    "6": {
        "prusaslicer": [
            "Creality/Creality Ender-3",
            "Creality/Creality Ender-3 BLTouch"
        ],
        "orcaslicer": [
            "Creality/Creality Ender-3"
        ],
        "elegooslicer": [
            "Creality/Creality Ender-3"
        ],
        "superslicer": [
            "Creality/Creality Ender-3",
            "Creality/Creality Ender-3 BLTouch"
        ]
    },
    "8": {
        "cura": [
            "Ultimaker B.V./Ultimaker 2+"
        ]
    },
    "9": {
        "prusaslicer": [
            "Creality/Creality CR-10 V2"
        ],
        "orcaslicer": [
            "Creality/Creality CR-10 V2"
        ],
        "bambustudio": [
            "Creality/Creality CR-10 V2"
        ],
        "elegooslicer": [
            "Creality/Creality CR-10 V2"
        ],
        "superslicer": [
            "Creality/Creality CR-10 V2"
        ]
    },
    "10": {
        "prusaslicer": [
            "Artillery/Artillery Sidewinder X1"
        ],
        "orcaslicer": [
            "Artillery/Artillery Sidewinder X1"
        ],
        "elegooslicer": [
            "Artillery/Artillery Sidewinder X1"
        ],
        "superslicer": [
            "Artillery/Artillery Sidewinder X1"
        ],
        "cura": [
            "Artillery/Artillery Sidewinder X1"
        ]
    },
    "11": {
        "prusaslicer": [
            "Creality/Creality CR-10 S Pro"
        ],
        "superslicer": [
            "Creality/Creality CR-10 S Pro"
        ],
        "cura": [
            "Creality3D/Creality CR-10S Pro"
        ]
    },
    "12": {
        "prusaslicer": [
            "PrusaResearch/Original Prusa i3 MK3",
            "PrusaResearch/Original Prusa i3 MK3 MMU2"
        ],
        "superslicer": [
            "PrusaResearch/Original Prusa i3 MK3",
            "PrusaResearch/Original Prusa i3 MK3 MMU2"
        ]
    },
    "13": {
        "prusaslicer": [
            "PrusaResearch/Original Prusa MINI && MINI+",
            "PrusaResearch/Original Prusa MINI && MINI+ Input Shaper"
        ],
        "orcaslicer": [
            "Prusa/Prusa MINI"
        ],
        "bambustudio": [
            "Prusa/Prusa MINI"
        ],
        "elegooslicer": [
            "Prusa/Prusa MINI"
        ],
        "superslicer": [
            "PrusaResearch/Original Prusa MINI && MINI+"
        ],
        "cura": [
            "Zav Co., Ltd./Zav Mini"
        ]
    },
    "15": {
        "cura": [
            "Prusa3D/Prusa i3 Mk2"
        ]
    },
    "16": {
        "prusaslicer": [
            "PrusaResearch/Original Prusa i3 MK2.5",
            "PrusaResearch/Original Prusa i3 MK2.5 MMU2"
        ],
        "superslicer": [
            "PrusaResearch/Original Prusa i3 MK2.5",
            "PrusaResearch/Original Prusa i3 MK2.5 MMU2"
        ]
    },
    "17": {
        "cura": [
            "Anet/Anet A8"
        ]
    },
    "18": {
        "prusaslicer": [
            "Anycubic/Anycubic i3 Mega"
        ],
        "superslicer": [
            "Anycubic/Anycubic i3 Mega"
        ],
        "cura": [
            "Anycubic/Anycubic i3 Mega"
        ]
    },
    "19": {
        "orcaslicer": [
            "Folgertech/Folgertech FT-5"
        ],
        "elegooslicer": [
            "Folgertech/Folgertech FT-5"
        ],
        "cura": [
            "Folger Tech/Folger Tech FT-5"
        ]
    },
    "20": {
        "prusaslicer": [
            "Creality/Creality CR-10 Max"
        ],
        "orcaslicer": [
            "Creality/Creality CR-10 Max"
        ],
        "bambustudio": [
            "Creality/Creality CR-10 Max"
        ],
        "elegooslicer": [
            "Creality/Creality CR-10 Max"
        ],
        "superslicer": [
            "Creality/Creality CR-10 Max"
        ],
        "cura": [
            "Creality3D/Creality CR-10 Max"
        ]
    },
    "24": {
        "prusaslicer": [
            "Creality/Creality CR-10 S Pro V2"
        ],
        "superslicer": [
            "Creality/Creality CR-10 S Pro V2"
        ]
    },
    "25": {
        "orcaslicer": [
            "Anycubic/Anycubic Chiron"
        ],
        "bambustudio": [
            "Anycubic/Anycubic Chiron"
        ],
        "elegooslicer": [
            "Anycubic/Anycubic Chiron"
        ],
        "cura": [
            "Anycubic/Anycubic Chiron"
        ]
    },
    "26": {
        "prusaslicer": [
            "Creality/Creality Ender-5 Plus"
        ],
        "orcaslicer": [
            "Creality/Creality Ender-5 Plus"
        ],
        "bambustudio": [
            "Creality/Creality Ender-5 Plus"
        ],
        "elegooslicer": [
            "Creality/Creality Ender-5 Plus"
        ],
        "superslicer": [
            "Creality/Creality Ender-5 Plus"
        ],
        "cura": [
            "Creality3D/Creality Ender-5 Plus"
        ]
    },
    "31": {
        "orcaslicer": [
            "Lulzbot/Lulzbot Taz 6"
        ],
        "elegooslicer": [
            "Lulzbot/Lulzbot Taz 6"
        ]
    },
    "37": {
        "cura": [
            "Tevo/Tevo Tarantula Pro"
        ]
    },
    "38": {
        "cura": [
            "Flsun/Flsun QQ"
        ]
    },
    "40": {
        "cura": [
            "Flsun/Flsun QQ-S"
        ]
    },
    "41": {
        "prusaslicer": [
            "Creality/Creality CR-10 Mini"
        ],
        "superslicer": [
            "Creality/Creality CR-10 Mini"
        ],
        "cura": [
            "Creality3D/Creality CR-10 Mini"
        ]
    },
    "42": {
        "prusaslicer": [
            "Creality/Creality Ender-3 Pro"
        ],
        "orcaslicer": [
            "Creality/Creality Ender-3 Pro"
        ],
        "elegooslicer": [
            "Creality/Creality Ender-3 Pro"
        ],
        "cura": [
            "Creality3D/Creality Ender-3 Pro"
        ]
    },
    "46": {
        "prusaslicer": [
            "Anycubic/Anycubic i3 Mega S"
        ],
        "orcaslicer": [
            "Anycubic/Anycubic i3 Mega S"
        ],
        "bambustudio": [
            "Anycubic/Anycubic i3 Mega S"
        ],
        "elegooslicer": [
            "Anycubic/Anycubic i3 Mega S"
        ],
        "superslicer": [
            "Anycubic/Anycubic i3 Mega S"
        ]
    },
    "47": {
        "cura": [
            "Tevo/Tevo Tornado"
        ]
    },
    "48": {
        "cura": [
            "Anet/Anet A6"
        ]
    },
    "50": {
        "cura": [
            "Wanhao/Wanhao Duplicator i3"
        ]
    },
    "51": {
        "cura": [
            "Flashforge/Adventurer 3"
        ]
    },
    "53": {
        "cura": [
            "Wanhao/Wanhao Duplicator 9"
        ]
    },
    "54": {
        "prusaslicer": [
            "Creality/Creality CR-20"
        ],
        "superslicer": [
            "Creality/Creality CR-20"
        ],
        "cura": [
            "Creality3D/Creality CR-20"
        ]
    },
    "55": {
        "prusaslicer": [
            "Creality/Creality CR-20 Pro"
        ],
        "superslicer": [
            "Creality/Creality CR-20 Pro"
        ],
        "cura": [
            "Creality3D/Creality CR-20 Pro"
        ]
    },
    "56": {
        "orcaslicer": [
            "Custom/Generic Klipper Printer",
            "Custom/Generic Marlin Printer",
            "Custom/Generic RRF Printer",
            "Custom/Generic ToolChanger Printer"
        ]
    },
    "57": {
        "orcaslicer": [
            "Custom/Generic Klipper Printer",
            "Custom/Generic Marlin Printer",
            "Custom/Generic RRF Printer",
            "Custom/Generic ToolChanger Printer"
        ]
    },
    "58": {
        "cura": [
            "Ultimaker B.V./Ultimaker Original"
        ]
    },
    "59": {
        "prusaslicer": [
            "Creality/Creality Ender-5 Pro"
        ]
    },
    "62": {
        "cura": [
            "Two Trees/Two Trees Sapphire Plus"
        ]
    },
    "63": {
        "cura": [
            "GooFoo/Goofoo Mido"
        ]
    },
    "64": {
        "prusaslicer": [
            "PrusaResearch/Original Prusa i3 MK3S && MK3S+",
            "PrusaResearch/Original Prusa i3 MK3S && MK3S+ MMU2S",
            "PrusaResearch/Original Prusa i3 MK3S && MK3S+ MMU3"
        ],
        "orcaslicer": [
            "Prusa/Prusa MK3S"
        ],
        "bambustudio": [
            "Prusa/Prusa MK3S"
        ],
        "elegooslicer": [
            "Prusa/Prusa MK3S"
        ],
        "superslicer": [
            "PrusaResearch/Original Prusa i3 MK3S && MK3S+",
            "PrusaResearch/Original Prusa i3 MK3S && MK3S+ MMU2S"
        ]
    },
    "68": {
        "cura": [
            "Anet/Anet ET4"
        ]
    },
    "69": {
        "cura": [
            "Anet/Anet ET4 Pro"
        ]
    },
    "72": {
        "prusaslicer": [
            "FLSun/FLSun Q5"
        ],
        "orcaslicer": [
            "FLSun/FLSun Q5"
        ],
        "elegooslicer": [
            "FLSun/FLSun Q5"
        ],
        "superslicer": [
            "FLSun/FLSun Q5"
        ],
        "cura": [
            "Flsun/Flsun Q5"
        ]
    },
    "73": {
        "prusaslicer": [
            "Creality/Creality Ender-3 V2"
        ],
        "orcaslicer": [
            "Creality/Creality Ender-3 V2"
        ],
        "bambustudio": [
            "Creality/Creality Ender-3 V2"
        ],
        "elegooslicer": [
            "Creality/Creality Ender-3 V2"
        ],
        "superslicer": [
            "Creality/Creality Ender-3 V2"
        ]
    },
    "76": {
        "prusaslicer": [
            "Creality/Creality CR-6 SE"
        ],
        "orcaslicer": [
            "Creality/Creality CR-6 SE"
        ],
        "bambustudio": [
            "Creality/Creality CR-6 SE"
        ],
        "elegooslicer": [
            "Creality/Creality CR-6 SE"
        ],
        "superslicer": [
            "Creality/Creality CR-6 SE"
        ],
        "cura": [
            "Creality3D/Creality CR-6 SE"
        ]
    },
    "79": {
        "prusaslicer": [
            "Creality/Creality Ender-6"
        ],
        "orcaslicer": [
            "Creality/Creality Ender-6"
        ],
        "bambustudio": [
            "Creality/Creality Ender-6"
        ],
        "elegooslicer": [
            "Creality/Creality Ender-6"
        ],
        "superslicer": [
            "Creality/Creality Ender-6"
        ],
        "cura": [
            "Creality3D/Creality Ender-6"
        ]
    },
    "80": {
        "prusaslicer": [
            "Artillery/Artillery Genius"
        ],
        "orcaslicer": [
            "Artillery/Artillery Genius"
        ],
        "elegooslicer": [
            "Artillery/Artillery Genius"
        ],
        "superslicer": [
            "Artillery/Artillery Genius"
        ],
        "cura": [
            "Artillery/Artillery Genius"
        ]
    },
    "82": {
        "cura": [
            "Anet/Anet E10"
        ]
    },
    "84": {
        "cura": [
            "Creality3D/Creality CR-X"
        ]
    },
    "85": {
        "orcaslicer": [
            "BIQU/BIQU B1"
        ],
        "elegooslicer": [
            "BIQU/BIQU B1"
        ],
        "cura": [
            "Biqu/Biqu B1"
        ]
    },
    "86": {
        "cura": [
            "GooFoo/Goofoo Nova"
        ]
    },
    "87": {
        "cura": [
            "GooFoo/Goofoo Plus"
        ]
    },
    "88": {
        "cura": [
            "Mingda/Mingda D2"
        ]
    },
    "89": {
        "prusaslicer": [
            "Ultimaker/Ultimaker 2"
        ],
        "orcaslicer": [
            "UltiMaker/UltiMaker 2"
        ],
        "elegooslicer": [
            "UltiMaker/UltiMaker 2"
        ],
        "superslicer": [
            "Ultimaker/Ultimaker 2"
        ],
        "cura": [
            "Ultimaker B.V./Ultimaker 2"
        ]
    },
    "90": {
        "cura": [
            "Monoprice/MP Mini Delta"
        ]
    },
    "93": {
        "prusaslicer": [
            "Anycubic/Anycubic Mega Zero"
        ],
        "superslicer": [
            "Anycubic/Anycubic Mega Zero"
        ],
        "cura": [
            "Anycubic/Anycubic Mega Zero"
        ]
    },
    "94": {
        "cura": [
            "GooFoo/Goofoo Mini+"
        ]
    },
    "98": {
        "cura": [
            "GooFoo/Goofoo Max"
        ]
    },
    "99": {
        "cura": [
            "GooFoo/Goofoo Tiny+"
        ]
    },
    "100": {
        "cura": [
            "GooFoo/Goofoo Tiny"
        ]
    },
    "102": {
        "prusaslicer": [
            "Creality/Creality CR-10 V3"
        ],
        "orcaslicer": [
            "Creality/Creality CR-10 V3"
        ],
        "elegooslicer": [
            "Creality/Creality CR-10 V3"
        ],
        "superslicer": [
            "Creality/Creality CR-10 V3"
        ]
    },
    "103": {
        "cura": [
            "Eryone/Eryone ER20"
        ]
    },
    "104": {
        "cura": [
            "Malyan/Malyan M200"
        ]
    },
    "106": {
        "orcaslicer": [
            "Sovol/Sovol SV01"
        ],
        "elegooslicer": [
            "Sovol/Sovol SV01"
        ],
        "cura": [
            "Sovol 3D/Sovol SV01"
        ]
    },
    "108": {
        "prusaslicer": [
            "Anycubic/Anycubic Predator"
        ],
        "superslicer": [
            "Anycubic/Anycubic Predator"
        ],
        "cura": [
            "Anycubic/Anycubic Predator"
        ]
    },
    "109": {
        "prusaslicer": [
            "Anycubic/Anycubic 4Max Pro 2.0"
        ],
        "superslicer": [
            "Anycubic/Anycubic 4Max Pro 2.0"
        ]
    },
    "110": {
        "orcaslicer": [
            "Anycubic/Anycubic 4Max Pro"
        ],
        "bambustudio": [
            "Anycubic/Anycubic 4Max Pro"
        ],
        "elegooslicer": [
            "Anycubic/Anycubic 4Max Pro"
        ]
    },
    "115": {
        "cura": [
            "Longer/Longer LK1"
        ]
    },
    "116": {
        "orcaslicer": [
            "Lulzbot/Lulzbot Taz Pro S"
        ],
        "elegooslicer": [
            "Lulzbot/Lulzbot Taz Pro S"
        ]
    },
    "120": {
        "prusaslicer": [
            "Creality/Creality Ender-3 Max"
        ],
        "superslicer": [
            "Creality/Creality Ender-3 Max"
        ],
        "cura": [
            "Creality3D/Creality Ender-3 Max"
        ]
    },
    "125": {
        "prusaslicer": [
            "Artillery/Artillery Hornet"
        ],
        "orcaslicer": [
            "Artillery/Artillery Hornet"
        ],
        "elegooslicer": [
            "Artillery/Artillery Hornet"
        ],
        "superslicer": [
            "Artillery/Artillery Hornet"
        ],
        "cura": [
            "Artillery/Artillery Hornet"
        ]
    },
    "126": {
        "cura": [
            "Sovol 3D/Sovol SV03"
        ]
    },
    "127": {
        "prusaslicer": [
            "Creality/Creality Ender-2"
        ],
        "superslicer": [
            "Creality/Creality Ender-2"
        ],
        "cura": [
            "Creality3D/Creality Ender-2"
        ]
    },
    "131": {
        "prusaslicer": [
            "Creality/Creality CR-6 Max"
        ],
        "orcaslicer": [
            "Creality/Creality CR-6 Max"
        ],
        "bambustudio": [
            "Creality/Creality CR-6 Max"
        ],
        "elegooslicer": [
            "Creality/Creality CR-6 Max"
        ],
        "superslicer": [
            "Creality/Creality CR-6 Max"
        ]
    },
    "132": {
        "orcaslicer": [
            "Sovol/Sovol SV02"
        ],
        "elegooslicer": [
            "Sovol/Sovol SV02"
        ]
    },
    "133": {
        "cura": [
            "Ultimaker B.V./Ultimaker 2 Go"
        ]
    },
    "140": {
        "cura": [
            "MakerGear/MakerGear M2"
        ]
    },
    "144": {
        "prusaslicer": [
            "BIQU/BIQU BX"
        ],
        "orcaslicer": [
            "BIQU/BIQU BX"
        ],
        "elegooslicer": [
            "BIQU/BIQU BX"
        ],
        "superslicer": [
            "BIQU/BIQU BX"
        ],
        "cura": [
            "Biqu/Biqu BX"
        ]
    },
    "146": {
        "cura": [
            "MakerBot/MakerBotReplicator"
        ]
    },
    "147": {
        "prusaslicer": [
            "Elegoo/Elegoo Neptune-2"
        ],
        "orcaslicer": [
            "Elegoo/Elegoo Neptune 2"
        ],
        "bambustudio": [
            "Elegoo/Elegoo Neptune 2"
        ],
        "elegooslicer": [
            "Elegoo/Elegoo Neptune 2"
        ],
        "superslicer": [
            "Elegoo/Elegoo Neptune-2"
        ],
        "cura": [
            "Elegoo/Neptune 2"
        ]
    },
    "148": {
        "orcaslicer": [
            "Elegoo/Elegoo Neptune"
        ],
        "bambustudio": [
            "Elegoo/Elegoo Neptune"
        ],
        "elegooslicer": [
            "Elegoo/Elegoo Neptune"
        ],
        "cura": [
            "ELEGOO/ELEGOO NEPTUNE"
        ]
    },
    "150": {
        "cura": [
            "Longer/Longer LK4 Pro"
        ]
    },
    "151": {
        "cura": [
            "Alfawise/Alfawise U20"
        ]
    },
    "157": {
        "cura": [
            "Hellbot/Hellbot Magna Dual"
        ]
    },
    "159": {
        "cura": [
            "Flying Bear/Flying Bear Ghost 5"
        ]
    },
    "162": {
        "cura": [
            "Wanhao/Wanhao Duplicator 4S"
        ]
    },
    "164": {
        "cura": [
            "Alfawise/Alfawise U30"
        ]
    },
    "168": {
        "orcaslicer": [
            "Qidi/Qidi X-Max"
        ],
        "bambustudio": [
            "Qidi/Qidi X-Max"
        ],
        "elegooslicer": [
            "Qidi/Qidi X-Max"
        ]
    },
    "171": {
        "cura": [
            "Geeetech/Geeetech A30"
        ]
    },
    "173": {
        "cura": [
            "Anet/Anet ET5"
        ]
    },
    "176": {
        "prusaslicer": [
            "Geeetech/Geeetech A10 M"
        ],
        "orcaslicer": [
            "Geeetech/Geeetech A10 M"
        ],
        "bambustudio": [
            "Geeetech/Geeetech A10 M"
        ],
        "elegooslicer": [
            "Geeetech/Geeetech A10 M"
        ],
        "cura": [
            "Geeetech/Geeetech A10M"
        ]
    },
    "177": {
        "cura": [
            "Geeetech/Geeetech A10"
        ]
    },
    "180": {
        "prusaslicer": [
            "Creality/Creality Sermoon-D1"
        ],
        "superslicer": [
            "Creality/Creality Sermoon-D1"
        ],
        "cura": [
            "Creality3D/Creality Sermoon D1"
        ]
    },
    "181": {
        "cura": [
            "Two Trees/Two Trees Sapphire Pro"
        ]
    },
    "186": {
        "cura": [
            "Lotmaxx/Lotmaxx SC-10"
        ]
    },
    "189": {
        "orcaslicer": [
            "Qidi/Qidi X-Plus"
        ],
        "bambustudio": [
            "Qidi/Qidi X-Plus"
        ],
        "elegooslicer": [
            "Qidi/Qidi X-Plus"
        ]
    },
    "195": {
        "cura": [
            "Wanhao/Wanhao Duplicator i3 Mini"
        ]
    },
    "197": {
        "orcaslicer": [
            "Dremel/Dremel 3D20"
        ],
        "elegooslicer": [
            "Dremel/Dremel 3D20"
        ]
    },
    "199": {
        "cura": [
            "Nwa 3D LLC/Nwa3D A31"
        ]
    },
    "206": {
        "orcaslicer": [
            "Voron/Voron 2.4 250",
            "Voron/Voron 2.4 300",
            "Voron/Voron 2.4 350"
        ],
        "bambustudio": [
            "Voron/Voron 2.4 250",
            "Voron/Voron 2.4 300",
            "Voron/Voron 2.4 350"
        ],
        "elegooslicer": [
            "Voron/Voron 2.4 250",
            "Voron/Voron 2.4 300",
            "Voron/Voron 2.4 350"
        ],
        "superslicer": [
            "Voron/Voron v2 250mm3",
            "Voron/Voron v2 300mm3",
            "Voron/Voron v2 350mm3"
        ],
        "cura": [
            "VoronDesign/Voron2 250",
            "VoronDesign/Voron2 300",
            "VoronDesign/Voron2 350",
            "VoronDesign/Voron2 Custom"
        ]
    },
    "207": {
        "superslicer": [
            "Voron/Voron v1 250mm3",
            "Voron/Voron v1 300mm3"
        ]
    },
    "212": {
        "prusaslicer": [
            "Creality/Creality CR-5 Pro"
        ],
        "superslicer": [
            "Creality/Creality CR-5 Pro"
        ]
    },
    "214": {
        "prusaslicer": [
            "Creality/Creality CR-5 Pro H"
        ],
        "superslicer": [
            "Creality/Creality CR-5 Pro H"
        ]
    },
    "215": {
        "prusaslicer": [
            "Geeetech/Geeetech A10 T"
        ],
        "orcaslicer": [
            "Geeetech/Geeetech A10 T"
        ],
        "bambustudio": [
            "Geeetech/Geeetech A10 T"
        ],
        "elegooslicer": [
            "Geeetech/Geeetech A10 T"
        ],
        "cura": [
            "Geeetech/Geeetech A10T"
        ]
    },
    "216": {
        "cura": [
            "Two Trees/Two Trees Bluer"
        ]
    },
    "218": {
        "prusaslicer": [
            "Geeetech/Geeetech A30 T"
        ],
        "orcaslicer": [
            "Geeetech/Geeetech A30 T"
        ],
        "bambustudio": [
            "Geeetech/Geeetech A30 T"
        ],
        "elegooslicer": [
            "Geeetech/Geeetech A30 T"
        ],
        "cura": [
            "Geeetech/Geeetech A30T"
        ]
    },
    "219": {
        "cura": [
            "Anet/Anet A8 Plus"
        ]
    },
    "223": {
        "cura": [
            "Kingroon/Kingroon KP3S"
        ]
    },
    "224": {
        "prusaslicer": [
            "Geeetech/Geeetech A20 M"
        ],
        "orcaslicer": [
            "Geeetech/Geeetech A20 M"
        ],
        "bambustudio": [
            "Geeetech/Geeetech A20 M"
        ],
        "elegooslicer": [
            "Geeetech/Geeetech A20 M"
        ],
        "cura": [
            "Geeetech/Geeetech A20M"
        ]
    },
    "225": {
        "cura": [
            "Tevo/Tevo Black Widow"
        ]
    },
    "227": {
        "cura": [
            "Deltaprintr/Delta Go"
        ]
    },
    "230": {
        "prusaslicer": [
            "Creality/Creality CR-200B"
        ],
        "superslicer": [
            "Creality/Creality CR-200B"
        ]
    },
    "233": {
        "prusaslicer": [
            "Geeetech/Geeetech A20 T"
        ],
        "orcaslicer": [
            "Geeetech/Geeetech A20 T"
        ],
        "bambustudio": [
            "Geeetech/Geeetech A20 T"
        ],
        "elegooslicer": [
            "Geeetech/Geeetech A20 T"
        ],
        "cura": [
            "Geeetech/Geeetech A20T"
        ]
    },
    "235": {
        "orcaslicer": [
            "Artillery/Artillery Sidewinder X2"
        ],
        "elegooslicer": [
            "Artillery/Artillery Sidewinder X2"
        ]
    },
    "236": {
        "prusaslicer": [
            "PrusaResearch/Original Prusa i3 MK3S && MK3S+",
            "PrusaResearch/Original Prusa i3 MK3S && MK3S+ MMU2S",
            "PrusaResearch/Original Prusa i3 MK3S && MK3S+ MMU3"
        ],
        "orcaslicer": [
            "Prusa/Prusa MK3S"
        ],
        "bambustudio": [
            "Prusa/Prusa MK3S"
        ],
        "elegooslicer": [
            "Prusa/Prusa MK3S"
        ],
        "superslicer": [
            "PrusaResearch/Original Prusa i3 MK3S && MK3S+",
            "PrusaResearch/Original Prusa i3 MK3S && MK3S+ MMU2S"
        ]
    },
    "238": {
        "prusaslicer": [
            "Creality/Creality Ender-7"
        ],
        "superslicer": [
            "Creality/Creality Ender-7"
        ]
    },
    "239": {
        "orcaslicer": [
            "Anycubic/Anycubic Vyper"
        ],
        "bambustudio": [
            "Anycubic/Anycubic Vyper"
        ],
        "elegooslicer": [
            "Anycubic/Anycubic Vyper"
        ],
        "cura": [
            "Anycubic/Anycubic Vyper"
        ]
    },
    "241": {
        "prusaslicer": [
            "Creality/Creality CR-10 SMART"
        ],
        "superslicer": [
            "Creality/Creality CR-10 SMART"
        ],
        "cura": [
            "Creality3D/Creality CR-10 Smart"
        ]
    },
    "243": {
        "prusaslicer": [
            "RatRig/RatRig V-Core-3.1 300mm"
        ],
        "orcaslicer": [
            "Ratrig/RatRig V-Core 3 300"
        ],
        "elegooslicer": [
            "Ratrig/RatRig V-Core 3 300"
        ],
        "superslicer": [
            "RatRig/RatRig V-Core-3 300mm"
        ],
        "cura": [
            "RatRig/RatRig V-Core 3 300mm"
        ]
    },
    "244": {
        "prusaslicer": [
            "RatRig/RatRig V-Core-3.1 400mm"
        ],
        "orcaslicer": [
            "Ratrig/RatRig V-Core 3 400"
        ],
        "elegooslicer": [
            "Ratrig/RatRig V-Core 3 400"
        ],
        "superslicer": [
            "RatRig/RatRig V-Core-3 400mm"
        ],
        "cura": [
            "RatRig/RatRig V-Core 3 400mm"
        ]
    },
    "245": {
        "prusaslicer": [
            "RatRig/RatRig V-Core-3.1 500mm"
        ],
        "orcaslicer": [
            "Ratrig/RatRig V-Core 3 500"
        ],
        "elegooslicer": [
            "Ratrig/RatRig V-Core 3 500"
        ],
        "superslicer": [
            "RatRig/RatRig V-Core-3 500mm"
        ],
        "cura": [
            "RatRig/RatRig V-Core 3 500mm"
        ]
    },
    "250": {
        "prusaslicer": [
            "Creality/Creality Ender-3 S1"
        ],
        "orcaslicer": [
            "Creality/Creality Ender-3 S1"
        ],
        "bambustudio": [
            "Creality/Creality Ender-3 S1"
        ],
        "elegooslicer": [
            "Creality/Creality Ender-3 S1"
        ],
        "superslicer": [
            "Creality/Creality Ender-3 S1"
        ],
        "cura": [
            "Creality3D/Creality Ender-3 S1"
        ]
    },
    "251": {
        "cura": [
            "Renkforce/Renkforce RF100 V2"
        ]
    },
    "252": {
        "cura": [
            "Flsun/Flsun Super Racer"
        ]
    },
    "253": {
        "prusaslicer": [
            "Zonestar/Zonestar Z8"
        ],
        "superslicer": [
            "Zonestar/Zonestar Z8"
        ]
    },
    "255": {
        "cura": [
            "Longer/Longer LK5 Pro"
        ]
    },
    "257": {
        "orcaslicer": [
            "Anycubic/Anycubic Kobra"
        ],
        "elegooslicer": [
            "Anycubic/Anycubic Kobra"
        ],
        "cura": [
            "Anycubic/Anycubic Kobra"
        ]
    },
    "258": {
        "orcaslicer": [
            "Anycubic/Anycubic Kobra Max"
        ],
        "bambustudio": [
            "Anycubic/Anycubic Kobra Max"
        ],
        "elegooslicer": [
            "Anycubic/Anycubic Kobra Max"
        ],
        "cura": [
            "Anycubic/Anycubic Kobra Max"
        ]
    },
    "267": {
        "prusaslicer": [
            "RatRig/RatRig V-Minion"
        ],
        "orcaslicer": [
            "Ratrig/RatRig V-Minion"
        ],
        "elegooslicer": [
            "Ratrig/RatRig V-Minion"
        ],
        "superslicer": [
            "RatRig/RatRig V-Minion"
        ],
        "cura": [
            "RatRig/RatRig V-Minion"
        ]
    },
    "282": {
        "cura": [
            "Mingda/Mingda Magician X"
        ]
    },
    "285": {
        "orcaslicer": [
            "FLSun/FLSun V400"
        ],
        "elegooslicer": [
            "FLSun/FLSun V400"
        ],
        "cura": [
            "Flsun/Flsun V400"
        ]
    },
    "288": {
        "prusaslicer": [
            "Creality/Creality Ender-2 Pro"
        ],
        "superslicer": [
            "Creality/Creality Ender-2 Pro"
        ]
    },
    "289": {
        "prusaslicer": [
            "Creality/Creality Ender-3 S1 Pro"
        ],
        "orcaslicer": [
            "Creality/Creality Ender-3 S1 Pro"
        ],
        "bambustudio": [
            "Creality/Creality Ender-3 S1 Pro"
        ],
        "elegooslicer": [
            "Creality/Creality Ender-3 S1 Pro"
        ],
        "cura": [
            "Creality3D/Creality Ender-3 S1 Pro"
        ]
    },
    "290": {
        "prusaslicer": [
            "Creality/Creality Ender-5 S1"
        ],
        "orcaslicer": [
            "Creality/Creality Ender-5 S1"
        ],
        "bambustudio": [
            "Creality/Creality Ender-5 S1"
        ],
        "elegooslicer": [
            "Creality/Creality Ender-5 S1"
        ],
        "cura": [
            "Creality3D/Creality Ender-5 S1"
        ]
    },
    "293": {
        "cura": [
            "Printrbot/Printrbot Play"
        ]
    },
    "295": {
        "orcaslicer": [
            "Sovol/Sovol SV06"
        ],
        "elegooslicer": [
            "Sovol/Sovol SV06"
        ],
        "cura": [
            "Sovol 3D/Sovol SV06"
        ]
    },
    "296": {
        "prusaslicer": [
            "Geeetech/Geeetech I3 ProB"
        ],
        "cura": [
            "Geeetech/Geeetech I3ProB"
        ]
    },
    "299": {
        "cura": [
            "Anycubic/Anycubic 4Max"
        ]
    },
    "301": {
        "prusaslicer": [
            "PrusaResearch/Original Prusa XL",
            "PrusaResearch/Original Prusa XL Input Shaper"
        ],
        "orcaslicer": [
            "Prusa/Prusa XL"
        ],
        "elegooslicer": [
            "Prusa/Prusa XL"
        ]
    },
    "306": {
        "prusaslicer": [
            "Elegoo/Elegoo Neptune-3 Pro"
        ],
        "orcaslicer": [
            "Elegoo/Elegoo Neptune 3 Pro"
        ],
        "bambustudio": [
            "Elegoo/Elegoo Neptune 3 Pro"
        ],
        "elegooslicer": [
            "Elegoo/Elegoo Neptune 3 Pro"
        ],
        "cura": [
            "ELEGOO/ELEGOO NEPTUNE 3 Pro"
        ]
    },
    "311": {
        "prusaslicer": [
            "Creality/Creality Ender-3 V2 Neo"
        ],
        "orcaslicer": [
            "Creality/Creality Ender-3 V2 Neo"
        ],
        "elegooslicer": [
            "Creality/Creality Ender-3 V2 Neo"
        ],
        "cura": [
            "Creality3D/Creality Ender-3 v2 Neo"
        ]
    },
    "312": {
        "prusaslicer": [
            "Creality/Creality Ender-3 Max Neo"
        ]
    },
    "313": {
        "prusaslicer": [
            "Creality/Creality Ender-3 Neo"
        ]
    },
    "314": {
        "prusaslicer": [
            "Creality/Creality Ender-3 S1 Plus"
        ],
        "orcaslicer": [
            "Creality/Creality Ender-3 S1 Plus"
        ],
        "elegooslicer": [
            "Creality/Creality Ender-3 S1 Plus"
        ],
        "cura": [
            "Creality3D/Creality Ender-3 S1 Plus"
        ]
    },
    "315": {
        "orcaslicer": [
            "Creality/Creality CR-M4"
        ],
        "elegooslicer": [
            "Creality/Creality CR-M4"
        ]
    },
    "317": {
        "orcaslicer": [
            "Voxelab/Voxelab Aquila X2"
        ],
        "bambustudio": [
            "Voxelab/Voxelab Aquila X2"
        ],
        "elegooslicer": [
            "Voxelab/Voxelab Aquila X2"
        ]
    },
    "320": {
        "prusaslicer": [
            "Elegoo/Elegoo Neptune-3"
        ],
        "orcaslicer": [
            "Elegoo/Elegoo Neptune 3"
        ],
        "bambustudio": [
            "Elegoo/Elegoo Neptune 3"
        ],
        "elegooslicer": [
            "Elegoo/Elegoo Neptune 3"
        ],
        "superslicer": [
            "Elegoo/Elegoo Neptune-3"
        ],
        "cura": [
            "ELEGOO/ELEGOO NEPTUNE 3"
        ]
    },
    "323": {
        "cura": [
            "Dagoma/Dagoma Magis"
        ]
    },
    "332": {
        "cura": [
            "Flashforge/Dreamer NX"
        ]
    },
    "335": {
        "orcaslicer": [
            "FlyingBear/FlyingBear Ghost 6"
        ],
        "elegooslicer": [
            "FlyingBear/FlyingBear Ghost 6"
        ],
        "cura": [
            "Flying Bear/Flying Bear Ghost 6"
        ]
    },
    "338": {
        "cura": [
            "Longer/Longer LK5 Pro"
        ]
    },
    "339": {
        "cura": [
            "Creasee/Creasee CS30"
        ]
    },
    "345": {
        "prusaslicer": [
            "Geeetech/Geeetech Me Creator2"
        ],
        "cura": [
            "Geeetech/Geeetech MeCreator2"
        ]
    },
    "346": {
        "cura": [
            "Mingda/Mingda Magician Pro"
        ]
    },
    "347": {
        "cura": [
            "Mingda/Mingda Magician Max"
        ]
    },
    "355": {
        "cura": [
            "Hellbot/Hellbot Magna 1"
        ]
    },
    "362": {
        "prusaslicer": [
            "Geeetech/Geeetech I3 ProC"
        ],
        "cura": [
            "Geeetech/Geeetech I3ProC"
        ]
    },
    "369": {
        "orcaslicer": [
            "Ratrig/RatRig V-Core 3 200"
        ],
        "elegooslicer": [
            "Ratrig/RatRig V-Core 3 200"
        ],
        "superslicer": [
            "RatRig/RatRig V-Core-3 200mm"
        ],
        "cura": [
            "RatRig/RatRig V-Core 3 200mm"
        ]
    },
    "373": {
        "cura": [
            "Dagoma/Dagoma DiscoUltimate"
        ]
    },
    "375": {
        "cura": [
            "Velleman N.V./Vertex K8400"
        ]
    },
    "377": {
        "cura": [
            "German RepRap/German RepRap Neo"
        ]
    },
    "379": {
        "cura": [
            "Mixware/Hyper S"
        ]
    },
    "384": {
        "cura": [
            "Hellbot/Hellbot Magna SE",
            "Hellbot/Hellbot Magna SE 300"
        ]
    },
    "388": {
        "prusaslicer": [
            "PrusaResearch/Original Prusa MINI && MINI+",
            "PrusaResearch/Original Prusa MINI && MINI+ Input Shaper"
        ],
        "orcaslicer": [
            "Prusa/Prusa MINI"
        ],
        "bambustudio": [
            "Prusa/Prusa MINI"
        ],
        "elegooslicer": [
            "Prusa/Prusa MINI"
        ],
        "superslicer": [
            "PrusaResearch/Original Prusa MINI && MINI+"
        ],
        "cura": [
            "Zav Co., Ltd./Zav Mini"
        ]
    },
    "392": {
        "orcaslicer": [
            "Anycubic/Anycubic Kobra Plus"
        ],
        "bambustudio": [
            "Anycubic/Anycubic Kobra Plus"
        ],
        "elegooslicer": [
            "Anycubic/Anycubic Kobra Plus"
        ],
        "cura": [
            "Anycubic/Anycubic Kobra Plus"
        ]
    },
    "394": {
        "prusaslicer": [
            "Anker/AnkerMake M5"
        ],
        "orcaslicer": [
            "Anker/Anker M5"
        ],
        "bambustudio": [
            "Anker/Anker M5"
        ],
        "elegooslicer": [
            "Anker/Anker M5"
        ],
        "cura": [
            "AnkerMake/AnkerMake M5"
        ]
    },
    "396": {
        "cura": [
            "Anycubic/Anycubic Kobra Go"
        ]
    },
    "400": {
        "prusaslicer": [
            "PrusaResearch/Original Prusa MK4",
            "PrusaResearch/Original Prusa MK4 Input Shaper",
            "PrusaResearch/Original Prusa MK4 MMU3"
        ],
        "orcaslicer": [
            "Prusa/Prusa MK4"
        ],
        "elegooslicer": [
            "Prusa/Prusa MK4"
        ]
    },
    "401": {
        "orcaslicer": [
            "Artillery/Artillery Genius Pro"
        ],
        "elegooslicer": [
            "Artillery/Artillery Genius Pro"
        ]
    },
    "404": {
        "orcaslicer": [
            "Sovol/Sovol SV06 Plus"
        ],
        "elegooslicer": [
            "Sovol/Sovol SV06 Plus"
        ]
    },
    "405": {
        "prusaslicer": [
            "Elegoo/Elegoo Neptune-3 Plus"
        ],
        "orcaslicer": [
            "Elegoo/Elegoo Neptune 3 Plus"
        ],
        "bambustudio": [
            "Elegoo/Elegoo Neptune 3 Plus"
        ],
        "elegooslicer": [
            "Elegoo/Elegoo Neptune 3 Plus"
        ],
        "cura": [
            "ELEGOO/ELEGOO NEPTUNE 3 Plus"
        ]
    },
    "406": {
        "orcaslicer": [
            "BBL/Bambu Lab P1P"
        ],
        "bambustudio": [
            "BBL/Bambu Lab P1P"
        ],
        "elegooslicer": [
            "BBL/Bambu Lab P1P"
        ]
    },
    "407": {
        "orcaslicer": [
            "BBL/Bambu Lab X1 Carbon"
        ],
        "bambustudio": [
            "BBL/Bambu Lab X1 Carbon"
        ],
        "elegooslicer": [
            "BBL/Bambu Lab X1 Carbon"
        ]
    },
    "408": {
        "orcaslicer": [
            "BBL/Bambu Lab X1 Carbon"
        ],
        "bambustudio": [
            "BBL/Bambu Lab X1 Carbon"
        ],
        "elegooslicer": [
            "BBL/Bambu Lab X1 Carbon"
        ]
    },
    "409": {
        "orcaslicer": [
            "Creality/Creality K1"
        ],
        "bambustudio": [
            "Creality/Creality K1"
        ],
        "elegooslicer": [
            "Creality/Creality K1"
        ]
    },
    "410": {
        "orcaslicer": [
            "Creality/Creality K1 Max"
        ],
        "bambustudio": [
            "Creality/Creality K1 Max"
        ],
        "elegooslicer": [
            "Creality/Creality K1 Max"
        ]
    },
    "411": {
        "orcaslicer": [
            "Anycubic/Anycubic Kobra 2"
        ],
        "bambustudio": [
            "Anycubic/Anycubic Kobra 2"
        ],
        "elegooslicer": [
            "Anycubic/Anycubic Kobra 2"
        ],
        "cura": [
            "Anycubic/Anycubic Kobra 2"
        ]
    },
    "412": {
        "cura": [
            "Ultimaker B.V./Ultimaker 2+ Connect"
        ]
    },
    "413": {
        "cura": [
            "Ultimaker B.V./UltiMaker S3"
        ]
    },
    "414": {
        "cura": [
            "Ultimaker B.V./UltiMaker S5"
        ]
    },
    "415": {
        "cura": [
            "Ultimaker B.V./UltiMaker S7"
        ]
    },
    "419": {
        "prusaslicer": [
            "Voron/VORON Trident 250mm",
            "Voron/VORON Trident 300mm",
            "Voron/VORON Trident 350mm"
        ],
        "orcaslicer": [
            "Voron/Voron Trident 250",
            "Voron/Voron Trident 300",
            "Voron/Voron Trident 350"
        ],
        "bambustudio": [
            "Voron/Voron Trident 250",
            "Voron/Voron Trident 300",
            "Voron/Voron Trident 350"
        ],
        "elegooslicer": [
            "Voron/Voron Trident 250",
            "Voron/Voron Trident 300",
            "Voron/Voron Trident 350"
        ],
        "cura": [
            "VoronDesign/Voron Trident 250",
            "VoronDesign/Voron Trident 300",
            "VoronDesign/Voron Trident 350"
        ]
    },
    "420": {
        "prusaslicer": [
            "Voron/VORON Zero"
        ],
        "orcaslicer": [
            "Voron/Voron 0.1"
        ],
        "bambustudio": [
            "Voron/Voron 0.1"
        ],
        "elegooslicer": [
            "Voron/Voron 0.1"
        ],
        "superslicer": [
            "Voron/Voron Zero 120mm3"
        ],
        "cura": [
            "VoronDesign/Voron 0"
        ]
    },
    "421": {
        "orcaslicer": [
            "Creality/Creality Ender-3 V3 SE"
        ],
        "elegooslicer": [
            "Creality/Creality Ender-3 V3 SE"
        ],
        "cura": [
            "Creality3D/Creality Ender-3 V3 SE"
        ]
    },
    "422": {
        "orcaslicer": [
            "Sovol/Sovol SV07"
        ],
        "elegooslicer": [
            "Sovol/Sovol SV07"
        ]
    },
    "423": {
        "orcaslicer": [
            "Sovol/Sovol SV07 Plus"
        ],
        "elegooslicer": [
            "Sovol/Sovol SV07 Plus"
        ]
    },
    "426": {
        "prusaslicer": [
            "QIDITechnology/X-smart 3"
        ],
        "orcaslicer": [
            "Qidi/Qidi X-Smart 3"
        ],
        "bambustudio": [
            "Qidi/Qidi X-Smart 3"
        ],
        "elegooslicer": [
            "Qidi/Qidi X-Smart 3"
        ]
    },
    "427": {
        "orcaslicer": [
            "Sovol/Sovol SV05"
        ],
        "elegooslicer": [
            "Sovol/Sovol SV05"
        ],
        "cura": [
            "Sovol 3D/Sovol SV05"
        ]
    },
    "430": {
        "orcaslicer": [
            "BBL/Bambu Lab A1 mini"
        ],
        "bambustudio": [
            "BBL/Bambu Lab A1 mini"
        ],
        "elegooslicer": [
            "BBL/Bambu Lab A1 mini"
        ]
    },
    "431": {
        "orcaslicer": [
            "BBL/Bambu Lab P1S"
        ],
        "bambustudio": [
            "BBL/Bambu Lab P1S"
        ],
        "elegooslicer": [
            "BBL/Bambu Lab P1S"
        ]
    },
    "432": {
        "prusaslicer": [
            "PrusaResearch/Original Prusa MK3.5 && MK3.5S",
            "PrusaResearch/Original Prusa MK3.5 && MK3.5S MMU3"
        ],
        "orcaslicer": [
            "Prusa/Prusa MK3.5",
            "Prusa/Prusa MK3S"
        ],
        "bambustudio": [
            "Prusa/Prusa MK3S"
        ],
        "elegooslicer": [
            "Prusa/Prusa MK3.5",
            "Prusa/Prusa MK3S"
        ]
    },
    "433": {
        "prusaslicer": [
            "PrusaResearch/Original Prusa MK3.9 Input Shaper",
            "PrusaResearch/Original Prusa MK3.9 MMU3",
            "PrusaResearch/Original Prusa MK4"
        ],
        "orcaslicer": [
            "Prusa/Prusa MK4"
        ],
        "elegooslicer": [
            "Prusa/Prusa MK4"
        ]
    },
    "434": {
        "orcaslicer": [
            "Prusa/Prusa MK3S"
        ],
        "bambustudio": [
            "Prusa/Prusa MK3S"
        ],
        "elegooslicer": [
            "Prusa/Prusa MK3S"
        ]
    },
    "435": {
        "orcaslicer": [
            "Prusa/Prusa MINI"
        ],
        "bambustudio": [
            "Prusa/Prusa MINI"
        ],
        "elegooslicer": [
            "Prusa/Prusa MINI"
        ],
        "cura": [
            "Zav Co., Ltd./Zav Mini"
        ]
    },
    "436": {
        "prusaslicer": [
            "PrusaResearch/Original Prusa MK4"
        ],
        "orcaslicer": [
            "Prusa/Prusa MK4"
        ],
        "elegooslicer": [
            "Prusa/Prusa MK4"
        ]
    },
    "437": {
        "orcaslicer": [
            "Prusa/Prusa MK3S"
        ],
        "bambustudio": [
            "Prusa/Prusa MK3S"
        ],
        "elegooslicer": [
            "Prusa/Prusa MK3S"
        ]
    },
    "438": {
        "orcaslicer": [
            "Prusa/Prusa MK3S"
        ],
        "bambustudio": [
            "Prusa/Prusa MK3S"
        ],
        "elegooslicer": [
            "Prusa/Prusa MK3S"
        ]
    },
    "440": {
        "cura": [
            "Ultimaker B.V./UltiMaker Method X"
        ]
    },
    "445": {
        "cura": [
            "Ultimaker B.V./UltiMaker Method XL"
        ]
    },
    "446": {
        "prusaslicer": [
            "Voron/VORON Switchwire"
        ],
        "orcaslicer": [
            "Voron/Voron Switchwire 250"
        ],
        "elegooslicer": [
            "Voron/Voron Switchwire 250"
        ]
    },
    "452": {
        "cura": [
            "WEEDO/WEEDO TINA2"
        ]
    },
    "453": {
        "prusaslicer": [
            "Geeetech/Geeetech Mizar M"
        ],
        "orcaslicer": [
            "Geeetech/Geeetech Mizar M"
        ],
        "bambustudio": [
            "Geeetech/Geeetech Mizar M"
        ],
        "elegooslicer": [
            "Geeetech/Geeetech Mizar M"
        ],
        "cura": [
            "Geeetech/Geeetech MizarM"
        ]
    },
    "455": {
        "prusaslicer": [
            "MakerGear/Ultra One"
        ],
        "superslicer": [
            "MakerGear/Ultra One"
        ]
    },
    "456": {
        "orcaslicer": [
            "Elegoo/Elegoo Neptune 4"
        ],
        "bambustudio": [
            "Elegoo/Elegoo Neptune 4"
        ],
        "elegooslicer": [
            "Elegoo/Elegoo Neptune 4"
        ],
        "cura": [
            "ELEGOO/ELEGOO NEPTUNE 4"
        ]
    },
    "457": {
        "orcaslicer": [
            "Elegoo/Elegoo Neptune 4 Pro"
        ],
        "bambustudio": [
            "Elegoo/Elegoo Neptune 4 Pro"
        ],
        "elegooslicer": [
            "Elegoo/Elegoo Neptune 4 Pro"
        ],
        "cura": [
            "ELEGOO/ELEGOO NEPTUNE 4 Pro"
        ]
    },
    "458": {
        "prusaslicer": [
            "Anycubic/Anycubic Kossel Linear Plus"
        ],
        "superslicer": [
            "Anycubic/Anycubic Kossel Linear Plus"
        ],
        "cura": [
            "Anycubic/Anycubic Kossel Linear Plus"
        ]
    },
    "459": {
        "cura": [
            "Anycubic/Anycubic Kossel Pulley"
        ]
    },
    "461": {
        "orcaslicer": [
            "BBL/Bambu Lab X1E"
        ],
        "bambustudio": [
            "BBL/Bambu Lab X1E"
        ],
        "elegooslicer": [
            "BBL/Bambu Lab X1E"
        ]
    },
    "462": {
        "orcaslicer": [
            "Anycubic/Anycubic Kobra 2 Max"
        ],
        "elegooslicer": [
            "Anycubic/Anycubic Kobra 2 Max"
        ]
    },
    "463": {
        "orcaslicer": [
            "Elegoo/Elegoo Neptune 4 Max"
        ],
        "bambustudio": [
            "Elegoo/Elegoo Neptune 4 Max"
        ],
        "elegooslicer": [
            "Elegoo/Elegoo Neptune 4 Max"
        ],
        "cura": [
            "ELEGOO/ELEGOO NEPTUNE 4 Max"
        ]
    },
    "467": {
        "orcaslicer": [
            "Elegoo/Elegoo Neptune 4 Plus"
        ],
        "bambustudio": [
            "Elegoo/Elegoo Neptune 4 Plus"
        ],
        "elegooslicer": [
            "Elegoo/Elegoo Neptune 4 Plus"
        ],
        "cura": [
            "ELEGOO/ELEGOO NEPTUNE 4 Plus"
        ]
    },
    "468": {
        "orcaslicer": [
            "Kingroon/Kingroon KP3S PRO V2"
        ],
        "elegooslicer": [
            "Kingroon/Kingroon KP3S PRO V2"
        ]
    },
    "469": {
        "orcaslicer": [
            "Creality/Creality Ender-3 V3 KE"
        ],
        "bambustudio": [
            "Creality/Creality Ender-3 V3 KE"
        ],
        "elegooslicer": [
            "Creality/Creality Ender-3 V3 KE"
        ]
    },
    "471": {
        "orcaslicer": [
            "Creality/Creality CR-10 SE"
        ],
        "elegooslicer": [
            "Creality/Creality CR-10 SE"
        ]
    },
    "472": {
        "orcaslicer": [
            "Creality/Creality K1C"
        ],
        "bambustudio": [
            "Creality/Creality K1C"
        ],
        "elegooslicer": [
            "Creality/Creality K1C"
        ]
    },
    "473": {
        "orcaslicer": [
            "Kingroon/Kingroon KLP1"
        ],
        "elegooslicer": [
            "Kingroon/Kingroon KLP1"
        ]
    },
    "474": {
        "cura": [
            "Kingroon/Kingroon KP3S Pro"
        ]
    },
    "475": {
        "orcaslicer": [
            "Kingroon/Kingroon KP3S 3.0"
        ],
        "elegooslicer": [
            "Kingroon/Kingroon KP3S 3.0"
        ]
    },
    "476": {
        "orcaslicer": [
            "BBL/Bambu Lab A1"
        ],
        "bambustudio": [
            "BBL/Bambu Lab A1"
        ],
        "elegooslicer": [
            "BBL/Bambu Lab A1"
        ]
    },
    "477": {
        "orcaslicer": [
            "BBL/Bambu Lab A1"
        ],
        "bambustudio": [
            "BBL/Bambu Lab A1"
        ],
        "elegooslicer": [
            "BBL/Bambu Lab A1"
        ]
    },
    "478": {
        "orcaslicer": [
            "BBL/Bambu Lab P1S"
        ],
        "bambustudio": [
            "BBL/Bambu Lab P1S"
        ],
        "elegooslicer": [
            "BBL/Bambu Lab P1S"
        ]
    },
    "479": {
        "orcaslicer": [
            "BBL/Bambu Lab A1 mini"
        ],
        "bambustudio": [
            "BBL/Bambu Lab A1 mini"
        ],
        "elegooslicer": [
            "BBL/Bambu Lab A1 mini"
        ]
    },
    "480": {
        "orcaslicer": [
            "Kingroon/Kingroon KP3S PRO S1"
        ],
        "elegooslicer": [
            "Kingroon/Kingroon KP3S PRO S1"
        ]
    },
    "481": {
        "orcaslicer": [
            "BIQU/BIQU Hurakan"
        ],
        "elegooslicer": [
            "BIQU/BIQU Hurakan"
        ],
        "cura": [
            "Biqu/Biqu Hurakan"
        ]
    },
    "482": {
        "prusaslicer": [
            "QIDITechnology/X-Plus 3"
        ],
        "orcaslicer": [
            "Qidi/Qidi X-Plus 3"
        ],
        "bambustudio": [
            "Qidi/Qidi X-Plus 3"
        ],
        "elegooslicer": [
            "Qidi/Qidi X-Plus 3"
        ]
    },
    "483": {
        "orcaslicer": [
            "Qidi/Qidi X-CF Pro"
        ],
        "bambustudio": [
            "Qidi/Qidi X-CF Pro"
        ],
        "elegooslicer": [
            "Qidi/Qidi X-CF Pro"
        ]
    },
    "487": {
        "prusaslicer": [
            "QIDITechnology/X-MAX 3"
        ],
        "orcaslicer": [
            "Qidi/Qidi X-Max 3"
        ],
        "bambustudio": [
            "Qidi/Qidi X-Max 3"
        ],
        "elegooslicer": [
            "Qidi/Qidi X-Max 3"
        ]
    },
    "489": {
        "orcaslicer": [
            "Sovol/Sovol SV01 Pro"
        ],
        "elegooslicer": [
            "Sovol/Sovol SV01 Pro"
        ],
        "cura": [
            "Sovol 3D/Sovol SV01PRO"
        ]
    },
    "490": {
        "orcaslicer": [
            "Anycubic/Anycubic Kobra 2 Neo"
        ],
        "elegooslicer": [
            "Anycubic/Anycubic Kobra 2 Neo"
        ]
    },
    "491": {
        "prusaslicer": [
            "Elegoo/Elegoo Neptune-3 Max"
        ],
        "orcaslicer": [
            "Elegoo/Elegoo Neptune 3 Max"
        ],
        "bambustudio": [
            "Elegoo/Elegoo Neptune 3 Max"
        ],
        "elegooslicer": [
            "Elegoo/Elegoo Neptune 3 Max"
        ],
        "cura": [
            "ELEGOO/ELEGOO NEPTUNE 3 Max"
        ]
    },
    "492": {
        "orcaslicer": [
            "Comgrow/Comgrow T500"
        ],
        "elegooslicer": [
            "Comgrow/Comgrow T500"
        ]
    },
    "497": {
        "prusaslicer": [
            "Creality/Creality CR-10 SMART Pro"
        ]
    },
    "498": {
        "orcaslicer": [
            "Creality/Creality CR-M4"
        ],
        "elegooslicer": [
            "Creality/Creality CR-M4"
        ]
    },
    "499": {
        "orcaslicer": [
            "Anycubic/Anycubic Kobra 2 Pro"
        ],
        "elegooslicer": [
            "Anycubic/Anycubic Kobra 2 Pro"
        ]
    },
    "500": {
        "orcaslicer": [
            "Anycubic/Anycubic Kobra 2 Plus"
        ],
        "elegooslicer": [
            "Anycubic/Anycubic Kobra 2 Plus"
        ]
    },
    "503": {
        "prusaslicer": [
            "Artillery/Artillery Sidewinder X3 Plus"
        ],
        "orcaslicer": [
            "Artillery/Artillery Sidewinder X3 Plus"
        ],
        "elegooslicer": [
            "Artillery/Artillery Sidewinder X3 Plus"
        ]
    },
    "505": {
        "cura": [
            "Flashforge/Adventurer 4"
        ]
    },
    "508": {
        "prusaslicer": [
            "Anker/AnkerMake M5C"
        ],
        "orcaslicer": [
            "Anker/Anker M5C"
        ],
        "bambustudio": [
            "Anker/Anker M5C"
        ],
        "elegooslicer": [
            "Anker/Anker M5C"
        ]
    },
    "515": {
        "orcaslicer": [
            "Comgrow/Comgrow T300"
        ],
        "elegooslicer": [
            "Comgrow/Comgrow T300"
        ]
    },
    "516": {
        "orcaslicer": [
            "Phrozen/Phrozen Arco"
        ],
        "elegooslicer": [
            "Phrozen/Phrozen Arco"
        ]
    },
    "517": {
        "prusaslicer": [
            "Artillery/Artillery Sidewinder X4 Pro"
        ],
        "orcaslicer": [
            "Artillery/Artillery Sidewinder X4 Pro"
        ],
        "elegooslicer": [
            "Artillery/Artillery Sidewinder X4 Pro"
        ]
    },
    "521": {
        "orcaslicer": [
            "Flashforge/Flashforge Adventurer 5M"
        ],
        "elegooslicer": [
            "Flashforge/Flashforge Adventurer 5M"
        ]
    },
    "522": {
        "orcaslicer": [
            "Flashforge/Flashforge Adventurer 5M Pro"
        ],
        "elegooslicer": [
            "Flashforge/Flashforge Adventurer 5M Pro"
        ]
    },
    "523": {
        "orcaslicer": [
            "Sovol/Sovol SV08"
        ],
        "elegooslicer": [
            "Sovol/Sovol SV08"
        ]
    },
    "526": {
        "prusaslicer": [
            "Snapmaker/Snapmaker Artisan"
        ],
        "orcaslicer": [
            "Snapmaker/Snapmaker Artisan"
        ],
        "elegooslicer": [
            "Snapmaker/Snapmaker Artisan"
        ]
    },
    "529": {
        "orcaslicer": [
            "BBL/Bambu Lab X1E"
        ],
        "bambustudio": [
            "BBL/Bambu Lab X1E"
        ],
        "elegooslicer": [
            "BBL/Bambu Lab X1E"
        ]
    },
    "530": {
        "prusaslicer": [
            "Artillery/Artillery Sidewinder X4 Plus"
        ],
        "orcaslicer": [
            "Artillery/Artillery Sidewinder X4 Plus"
        ],
        "elegooslicer": [
            "Artillery/Artillery Sidewinder X4 Plus"
        ]
    },
    "534": {
        "orcaslicer": [
            "Peopoly/Peopoly Magneto X"
        ],
        "elegooslicer": [
            "Peopoly/Peopoly Magneto X"
        ]
    },
    "536": {
        "cura": [
            "Nwa 3D LLC/Nwa3D A5"
        ]
    },
    "538": {
        "orcaslicer": [
            "BBL/Bambu Lab P1P"
        ],
        "bambustudio": [
            "BBL/Bambu Lab P1P"
        ],
        "elegooslicer": [
            "BBL/Bambu Lab P1P"
        ]
    },
    "539": {
        "superslicer": [
            "Meltingplot/Meltingplot MBL 136"
        ]
    },
    "540": {
        "superslicer": [
            "Meltingplot/Meltingplot MBL 308"
        ]
    },
    "541": {
        "superslicer": [
            "Meltingplot/Meltingplot MBL 480"
        ]
    },
    "542": {
        "orcaslicer": [
            "Anycubic/Anycubic Kobra 3"
        ],
        "elegooslicer": [
            "Anycubic/Anycubic Kobra 3"
        ]
    },
    "544": {
        "prusaslicer": [
            "PrusaResearch/Original Prusa MK4S",
            "PrusaResearch/Original Prusa MK4S MMU3"
        ],
        "orcaslicer": [
            "Prusa/Prusa MK4S"
        ],
        "elegooslicer": [
            "Prusa/Prusa MK4S"
        ]
    },
    "545": {
        "orcaslicer": [
            "Creality/Creality Ender-3 V3 Plus"
        ],
        "bambustudio": [
            "Creality/Creality Ender-3 V3 Plus"
        ],
        "elegooslicer": [
            "Creality/Creality Ender-3 V3 Plus"
        ]
    },
    "547": {
        "prusaslicer": [
            "QIDITechnology/Q1 Pro"
        ],
        "orcaslicer": [
            "Qidi/Qidi Q1 Pro"
        ],
        "bambustudio": [
            "Qidi/Qidi Q1 Pro"
        ],
        "elegooslicer": [
            "Qidi/Qidi Q1 Pro"
        ]
    },
    "548": {
        "prusaslicer": [
            "Artillery/Artillery Sidewinder X3 Pro"
        ],
        "orcaslicer": [
            "Artillery/Artillery Sidewinder X3 Pro"
        ],
        "elegooslicer": [
            "Artillery/Artillery Sidewinder X3 Pro"
        ]
    },
    "550": {
        "orcaslicer": [
            "BBL/Bambu Lab A1 mini"
        ],
        "bambustudio": [
            "BBL/Bambu Lab A1 mini"
        ],
        "elegooslicer": [
            "BBL/Bambu Lab A1 mini"
        ]
    },
    "551": {
        "orcaslicer": [
            "Creality/Creality K2 Plus"
        ],
        "elegooslicer": [
            "Creality/Creality K2 Plus"
        ]
    },
    "554": {
        "prusaslicer": [
            "PrusaResearch/Prusa CORE One && CORE One+",
            "PrusaResearch/Prusa CORE One && CORE One+ MMU3"
        ],
        "orcaslicer": [
            "Prusa/Prusa CORE One"
        ],
        "elegooslicer": [
            "Prusa/Prusa CORE One"
        ]
    },
    "555": {
        "orcaslicer": [
            "Ratrig/RatRig V-Core 4 300",
            "Ratrig/RatRig V-Core 4 HYBRID 300"
        ],
        "elegooslicer": [
            "Ratrig/RatRig V-Core 4 300",
            "Ratrig/RatRig V-Core 4 HYBRID 300"
        ]
    },
    "556": {
        "orcaslicer": [
            "Ratrig/RatRig V-Core 4 400",
            "Ratrig/RatRig V-Core 4 HYBRID 400"
        ],
        "elegooslicer": [
            "Ratrig/RatRig V-Core 4 400",
            "Ratrig/RatRig V-Core 4 HYBRID 400"
        ]
    },
    "557": {
        "orcaslicer": [
            "Ratrig/RatRig V-Core 4 500",
            "Ratrig/RatRig V-Core 4 HYBRID 500"
        ],
        "elegooslicer": [
            "Ratrig/RatRig V-Core 4 500",
            "Ratrig/RatRig V-Core 4 HYBRID 500"
        ]
    },
    "558": {
        "orcaslicer": [
            "Ratrig/RatRig V-Core 4 IDEX 300 COPY MODE",
            "Ratrig/RatRig V-Core 4 IDEX 300 MIRROR MODE",
            "Ratrig/RatRig V-Core 4 IDEX 300"
        ],
        "elegooslicer": [
            "Ratrig/RatRig V-Core 4 IDEX 300 COPY MODE",
            "Ratrig/RatRig V-Core 4 IDEX 300 MIRROR MODE",
            "Ratrig/RatRig V-Core 4 IDEX 300"
        ]
    },
    "559": {
        "orcaslicer": [
            "Ratrig/RatRig V-Core 4 IDEX 400 COPY MODE",
            "Ratrig/RatRig V-Core 4 IDEX 400 MIRROR MODE",
            "Ratrig/RatRig V-Core 4 IDEX 400"
        ],
        "elegooslicer": [
            "Ratrig/RatRig V-Core 4 IDEX 400 COPY MODE",
            "Ratrig/RatRig V-Core 4 IDEX 400 MIRROR MODE",
            "Ratrig/RatRig V-Core 4 IDEX 400"
        ]
    },
    "560": {
        "orcaslicer": [
            "Ratrig/RatRig V-Core 4 IDEX 500 COPY MODE",
            "Ratrig/RatRig V-Core 4 IDEX 500 MIRROR MODE",
            "Ratrig/RatRig V-Core 4 IDEX 500"
        ],
        "elegooslicer": [
            "Ratrig/RatRig V-Core 4 IDEX 500 COPY MODE",
            "Ratrig/RatRig V-Core 4 IDEX 500 MIRROR MODE",
            "Ratrig/RatRig V-Core 4 IDEX 500"
        ]
    },
    "573": {
        "orcaslicer": [
            "BBL/Bambu Lab A1 mini"
        ],
        "bambustudio": [
            "BBL/Bambu Lab A1 mini"
        ],
        "elegooslicer": [
            "BBL/Bambu Lab A1 mini"
        ]
    },
    "577": {
        "orcaslicer": [
            "BBL/Bambu Lab A1"
        ],
        "bambustudio": [
            "BBL/Bambu Lab A1"
        ],
        "elegooslicer": [
            "BBL/Bambu Lab A1"
        ]
    },
    "578": {
        "orcaslicer": [
            "BBL/Bambu Lab A1 mini"
        ],
        "bambustudio": [
            "BBL/Bambu Lab A1 mini"
        ],
        "elegooslicer": [
            "BBL/Bambu Lab A1 mini"
        ]
    },
    "579": {
        "bambustudio": [
            "BBL/Bambu Lab H2D"
        ]
    },
    "580": {
        "bambustudio": [
            "BBL/Bambu Lab H2D"
        ]
    },
    "581": {
        "bambustudio": [
            "BBL/Bambu Lab H2D"
        ]
    },
    "582": {
        "bambustudio": [
            "BBL/Bambu Lab H2D"
        ]
    },
    "585": {
        "orcaslicer": [
            "Anycubic/Anycubic Kobra S1"
        ],
        "elegooslicer": [
            "Anycubic/Anycubic Kobra S1"
        ]
    },
    "586": {
        "orcaslicer": [
            "FLSun/FLSun S1"
        ],
        "elegooslicer": [
            "FLSun/FLSun S1"
        ]
    },
    "587": {
        "cura": [
            "Ultimaker B.V./Ultimaker 3 Extended"
        ]
    },
    "588": {
        "cura": [
            "Ultimaker B.V./Ultimaker 3"
        ]
    },
    "591": {
        "orcaslicer": [
            "Elegoo/Elegoo Centauri Carbon"
        ],
        "elegooslicer": [
            "Elegoo/Elegoo Centauri Carbon"
        ]
    },
    "594": {
        "orcaslicer": [
            "Sovol/Sovol Zero"
        ],
        "elegooslicer": [
            "Sovol/Sovol Zero"
        ]
    },
    "596": {
        "orcaslicer": [
            "Creality/Creality Ender-5 Max"
        ],
        "elegooslicer": [
            "Creality/Creality Ender-5 Max"
        ]
    },
    "599": {
        "bambustudio": [
            "BBL/Bambu Lab H2S"
        ]
    },
    "600": {
        "bambustudio": [
            "BBL/Bambu Lab H2D Pro",
            "BBL/Bambu Lab H2D"
        ]
    },
    "601": {
        "bambustudio": [
            "BBL/Bambu Lab H2D"
        ]
    },
    "602": {
        "bambustudio": [
            "BBL/Bambu Lab H2S"
        ]
    },
    "604": {
        "orcaslicer": [
            "Creality/Creality Hi"
        ],
        "elegooslicer": [
            "Creality/Creality Hi"
        ]
    },
    "609": {
        "orcaslicer": [
            "BBL/Bambu Lab A1"
        ],
        "bambustudio": [
            "BBL/Bambu Lab A1"
        ],
        "elegooslicer": [
            "BBL/Bambu Lab A1"
        ]
    },
    "610": {
        "orcaslicer": [
            "Qidi/Qidi Q2"
        ],
        "elegooslicer": [
            "Qidi/Qidi Q2"
        ]
    },
    "614": {
        "bambustudio": [
            "BBL/Bambu Lab P2S"
        ]
    },
    "615": {
        "bambustudio": [
            "BBL/Bambu Lab P2S"
        ]
    },
    "616": {
        "orcaslicer": [
            "Kentstrapper/Kentstrapper ZeroHS CC"
        ]
    },
    "617": {
        "orcaslicer": [
            "Kentstrapper/Kentstrapper ZeroHS"
        ]
    },
    "618": {
        "orcaslicer": [
            "Kentstrapper/Kentstrapper B755"
        ]
    },
    "619": {
        "orcaslicer": [
            "Kentstrapper/Kentstrapper MAVIS"
        ]
    },
    "620": {
        "orcaslicer": [
            "Kentstrapper/Kentstrapper ZeroPro"
        ]
    },
    "621": {
        "orcaslicer": [
            "Kentstrapper/Kentstrapper VERVE"
        ]
    },
    "622": {
        "orcaslicer": [
            "BBL/Bambu Lab A1 mini"
        ],
        "bambustudio": [
            "BBL/Bambu Lab A1 mini"
        ],
        "elegooslicer": [
            "BBL/Bambu Lab A1 mini"
        ]
    },
    "623": {
        "orcaslicer": [
            "BBL/Bambu Lab A1 mini"
        ],
        "bambustudio": [
            "BBL/Bambu Lab A1 mini"
        ],
        "elegooslicer": [
            "BBL/Bambu Lab A1 mini"
        ]
    },
    "624": {
        "orcaslicer": [
            "BBL/Bambu Lab A1"
        ],
        "bambustudio": [
            "BBL/Bambu Lab A1"
        ],
        "elegooslicer": [
            "BBL/Bambu Lab A1"
        ]
    },
    "625": {
        "orcaslicer": [
            "BBL/Bambu Lab A1"
        ],
        "bambustudio": [
            "BBL/Bambu Lab A1"
        ],
        "elegooslicer": [
            "BBL/Bambu Lab A1"
        ]
    },
    "626": {
        "orcaslicer": [
            "BBL/Bambu Lab P1S"
        ],
        "bambustudio": [
            "BBL/Bambu Lab P1S"
        ],
        "elegooslicer": [
            "BBL/Bambu Lab P1S"
        ]
    },
    "627": {
        "orcaslicer": [
            "BBL/Bambu Lab X1 Carbon"
        ],
        "bambustudio": [
            "BBL/Bambu Lab X1 Carbon"
        ],
        "elegooslicer": [
            "BBL/Bambu Lab X1 Carbon"
        ]
    },
    "628": {
        "orcaslicer": [
            "BBL/Bambu Lab X1 Carbon"
        ],
        "bambustudio": [
            "BBL/Bambu Lab X1 Carbon"
        ],
        "elegooslicer": [
            "BBL/Bambu Lab X1 Carbon"
        ]
    },
    "629": {
        "orcaslicer": [
            "BBL/Bambu Lab P1S"
        ],
        "bambustudio": [
            "BBL/Bambu Lab P1S"
        ],
        "elegooslicer": [
            "BBL/Bambu Lab P1S"
        ]
    },
    "630": {
        "orcaslicer": [
            "Flashforge/Flashforge AD5X"
        ],
        "elegooslicer": [
            "Flashforge/Flashforge AD5X"
        ]
    },
    "633": {
        "orcaslicer": [
            "Creality/Creality K1 SE"
        ],
        "elegooslicer": [
            "Creality/Creality K1 SE"
        ]
    },
    "634": {
        "orcaslicer": [
            "Sovol/Sovol SV06 ACE"
        ],
        "elegooslicer": [
            "Sovol/Sovol SV06 ACE"
        ]
    },
    "635": {
        "orcaslicer": [
            "Sovol/Sovol SV06 Plus ACE"
        ],
        "elegooslicer": [
            "Sovol/Sovol SV06 Plus ACE"
        ]
    },
    "642": {
        "orcaslicer": [
            "Sovol/Sovol SV08 MAX"
        ],
        "elegooslicer": [
            "Sovol/Sovol SV08 MAX"
        ]
    },
    "644": {
        "prusaslicer": [
            "MakerGear/MakerGear M2 Dual"
        ],
        "superslicer": [
            "MakerGear/MakerGear M2 Dual"
        ]
    },
    "645": {
        "bambustudio": [
            "BBL/Bambu Lab H2C"
        ]
    },
    "646": {
        "bambustudio": [
            "BBL/Bambu Lab H2C"
        ]
    },
    "647": {
        "orcaslicer": [
            "Snapmaker/Snapmaker U1"
        ],
        "elegooslicer": [
            "Snapmaker/Snapmaker U1"
        ]
    }
}