{
  "slicer": "cura",
  "profile_type": "print",
  "name": "Super Quality · @tank_m_base",
  "vendor": "tank_m",
  "first_seen": "5.13.0",
  "last_seen": "5.13.0",
  "filament_id": null,
  "setting_id": "quality:tank_m_base:tank_m_base_global_high",
  "renamed_from": null,
  "filament_type": null,
  "native_id": "quality:tank_m_base:tank_m_base_global_high",
  "context": {
    "native_id": "quality:tank_m_base:tank_m_base_global_high",
    "source_kind": "quality",
    "resource_version": "5.13.0",
    "definition": "tank_m_base",
    "quality_type": "high",
    "intent_category": null,
    "variant_name": null,
    "material_id": null,
    "global_quality_id": null,
    "compatibility": {
      "machine_definition_ids": [
        "tank_m_base"
      ]
    }
  },
  "setting_scopes": {
    "layer_height_0": "global",
    "support_interface_height": "extruder.0",
    "layer_height": "global",
    "wall_thickness": "extruder.0",
    "top_bottom_thickness": "extruder.0"
  },
  "settings": {
    "layer_height_0": {
      "5.13.0": 0.12
    },
    "support_interface_height": {
      "5.13.0": 0.96
    },
    "layer_height": {
      "5.13.0": 0.12
    },
    "wall_thickness": {
      "5.13.0": 1.2000000000000002
    },
    "top_bottom_thickness": {
      "5.13.0": 0.84
    }
  }
}