{
  "slicer": "orcaslicer",
  "profile_type": "machine_model",
  "name": "Thinker X400",
  "vendor": "Eryone",
  "first_seen": "2.3.1",
  "last_seen": "2.3.1",
  "filament_id": null,
  "setting_id": null,
  "renamed_from": null,
  "settings": {
    "type": {
      "2.3.1": "machine_model"
    },
    "name": {
      "2.3.1": "Thinker X400"
    },
    "model_id": {
      "2.3.1": "Thinker-X400"
    },
    "nozzle_diameter": {
      "2.3.1": "0.4"
    },
    "machine_tech": {
      "2.3.1": "FFF"
    },
    "family": {
      "2.3.1": "Eryone"
    },
    "bed_model": {
      "2.3.1": "sha256:81c32fcc80552b7e5ee951dd9a73da47640924e5bae25f65299d9072f02a76a0"
    },
    "bed_texture": {
      "2.3.1": "sha256:6c33054a578add567122d4c7168f45cc2f1d6338e8678b9d59ace4783c6c936f"
    },
    "hotend_model": {
      "2.3.1": ""
    },
    "default_materials": {
      "2.3.1": "Eryone PLA;Eryone ABS;Eryone ASA;Eryone PETG;Eryone Silk PLA;Eryone TPU;Eryone ABS-CF;Eryone ASA-CF;Eryone PA;Eryone PA-CF;Eryone PA-GF;Eryone PETG-CF;Eryone PLA-CF;Eryone PP;Eryone PP-CF"
    }
  }
}