{
  "slicer": "cura",
  "profile_type": "print",
  "name": "Draft · @anycubic_4max · generic_abs",
  "vendor": "Anycubic",
  "first_seen": "5.13.0",
  "last_seen": "5.13.0",
  "filament_id": null,
  "setting_id": "quality:anycubic_4max:anycubic_4max/abs/anycubic_4max_abs_draft",
  "renamed_from": null,
  "filament_type": null,
  "native_id": "quality:anycubic_4max:anycubic_4max/abs/anycubic_4max_abs_draft",
  "context": {
    "native_id": "quality:anycubic_4max:anycubic_4max/abs/anycubic_4max_abs_draft",
    "source_kind": "quality",
    "resource_version": "5.13.0",
    "definition": "anycubic_4max",
    "quality_type": "draft",
    "intent_category": null,
    "variant_name": null,
    "material_id": "generic_abs",
    "global_quality_id": "quality:anycubic_4max:anycubic_4max/anycubic_4max_draft",
    "compatibility": {
      "machine_definition_ids": [
        "anycubic_4max"
      ],
      "material_native_ids": [
        "generic_abs"
      ]
    }
  },
  "setting_scopes": {
    "cool_fan_enabled": "extruder.0",
    "adhesion_type": "global",
    "layer_height": "global"
  },
  "settings": {
    "cool_fan_enabled": {
      "5.13.0": false
    },
    "adhesion_type": {
      "5.13.0": "brim"
    },
    "layer_height": {
      "5.13.0": 0.3
    }
  }
}