[
    {
        "machine_model": {
            "bed_model": "sha256:21224f498b7545778b192ffee4b443147919e791a2d62f2f74d29a5a19e9cd4d",
            "bed_texture": "sha256:f0603a565a553ac63b245ddd83af1ac677bf20237633f981c47708a972cdbe1f",
            "default_materials": "Generic PLA @Zonestar; Generic ABS @Zonestar; Generic PETG @Zonestar; Generic TPU @Zonestar",
            "name": "Zonestar Z8",
            "technology": "FFF",
            "variants": "0.4"
        },
        "variants": {},
        "vendor": "Zonestar"
    }
]