{
  "slicer": "orcaslicer",
  "profile_type": "machine_model",
  "name": "FLSun V400",
  "vendor": "FLSun",
  "first_seen": "2.3.1",
  "last_seen": "2.3.1",
  "filament_id": null,
  "setting_id": null,
  "renamed_from": null,
  "settings": {
    "type": {
      "2.3.1": "machine_model"
    },
    "name": {
      "2.3.1": "FLSun V400"
    },
    "model_id": {
      "2.3.1": "FLSun_V400"
    },
    "nozzle_diameter": {
      "2.3.1": "0.4"
    },
    "machine_tech": {
      "2.3.1": "FFF"
    },
    "family": {
      "2.3.1": "FLSun"
    },
    "bed_model": {
      "2.3.1": "sha256:841bca59e98838fef32fe48581f4fdf13ca0d0630163f307b945a74d97bbbc60"
    },
    "bed_texture": {
      "2.3.1": "sha256:a33168a61f666a5654aa1cc37fe86ddf85a8179661e2d6b472d02d5378e72f24"
    },
    "hotend_model": {
      "2.3.1": ""
    },
    "default_materials": {
      "2.3.1": "FLSun Generic ABS;FLSun Generic PLA;FLSun Generic PLA-CF;FLSun Generic PETG;FLSun Generic TPU;FLSun Generic ASA;FLSun Generic PC;FLSun Generic PVA;FLSun Generic PA;FLSun Generic PA-CF"
    }
  }
}