{
  "slicer": "cura",
  "profile_type": "print",
  "name": "Medium-Fine · @dagoma_pro_430_dual · Serie 0.2mm · generic_pla",
  "vendor": "Dagoma",
  "first_seen": "5.13.0",
  "last_seen": "5.13.0",
  "filament_id": null,
  "setting_id": "quality:dagoma_pro_430_dual:dagoma/dagoma_pro_430_dual_generic_0.2_pla_h0.15",
  "renamed_from": null,
  "filament_type": null,
  "native_id": "quality:dagoma_pro_430_dual:dagoma/dagoma_pro_430_dual_generic_0.2_pla_h0.15",
  "context": {
    "native_id": "quality:dagoma_pro_430_dual:dagoma/dagoma_pro_430_dual_generic_0.2_pla_h0.15",
    "source_kind": "quality",
    "resource_version": "5.13.0",
    "definition": "dagoma_pro_430_dual",
    "quality_type": "h0.15",
    "intent_category": null,
    "variant_name": "Serie 0.2mm",
    "material_id": "generic_pla",
    "global_quality_id": "quality:dagoma_pro_430_dual:dagoma/dagoma_pro_430_dual_global_h0.15",
    "compatibility": {
      "machine_definition_ids": [
        "dagoma_pro_430_dual"
      ],
      "variant_names": [
        "Serie 0.2mm"
      ],
      "material_native_ids": [
        "generic_pla"
      ]
    }
  },
  "setting_scopes": {
    "layer_height": "global"
  },
  "settings": {
    "layer_height": {
      "5.13.0": 0.15
    }
  }
}