{
  "slicer": "cura",
  "profile_type": "print",
  "name": "Draft Quality · @two_trees_base · 1.0mm Nozzle · generic_abs",
  "vendor": "Two Trees",
  "first_seen": "5.13.0",
  "last_seen": "5.13.0",
  "filament_id": null,
  "setting_id": "quality:two_trees_base:twotrees/abs/two_trees_1.0_ABS_draft",
  "renamed_from": null,
  "filament_type": null,
  "native_id": "quality:two_trees_base:twotrees/abs/two_trees_1.0_ABS_draft",
  "context": {
    "native_id": "quality:two_trees_base:twotrees/abs/two_trees_1.0_ABS_draft",
    "source_kind": "quality",
    "resource_version": "5.13.0",
    "definition": "two_trees_base",
    "quality_type": "draft",
    "intent_category": null,
    "variant_name": "1.0mm Nozzle",
    "material_id": "generic_abs",
    "global_quality_id": "quality:two_trees_base:twotrees/two_trees_global_draft",
    "compatibility": {
      "machine_definition_ids": [
        "two_trees_base"
      ],
      "variant_names": [
        "1.0mm Nozzle"
      ],
      "material_native_ids": [
        "generic_abs"
      ]
    }
  },
  "setting_scopes": {
    "layer_height_0": "global",
    "material_print_temperature": "extruder.0",
    "cool_fan_enabled": "extruder.0",
    "material_print_temperature_layer_0": "extruder.0",
    "support_interface_height": "extruder.0",
    "retraction_hop": "extruder.0",
    "layer_height": "global",
    "material_initial_print_temperature": "extruder.0",
    "material_standby_temperature": "extruder.0",
    "retraction_hop_only_when_collides": "extruder.0",
    "wall_thickness": "extruder.0",
    "top_bottom_thickness": "extruder.0",
    "material_bed_temperature": "global",
    "material_final_print_temperature": "extruder.0"
  },
  "settings": {
    "layer_height_0": {
      "5.13.0": 0.32
    },
    "material_print_temperature": {
      "5.13.0": 240
    },
    "cool_fan_enabled": {
      "5.13.0": false
    },
    "material_print_temperature_layer_0": {
      "5.13.0": 245
    },
    "support_interface_height": {
      "5.13.0": 1.28
    },
    "retraction_hop": {
      "5.13.0": 0.4
    },
    "layer_height": {
      "5.13.0": 0.32
    },
    "material_initial_print_temperature": {
      "5.13.0": 240
    },
    "material_standby_temperature": {
      "5.13.0": 240
    },
    "retraction_hop_only_when_collides": {
      "5.13.0": true
    },
    "wall_thickness": {
      "5.13.0": 0.8
    },
    "top_bottom_thickness": {
      "5.13.0": 1.28
    },
    "material_bed_temperature": {
      "5.13.0": 100
    },
    "material_final_print_temperature": {
      "5.13.0": 240
    }
  }
}