{
  "slicer": "kirimoto",
  "profile_type": "filament",
  "name": "JB2 PETG - N0.4 L0.3 T235",
  "vendor": "IMADE3D",
  "first_seen": "4.7.1",
  "last_seen": "4.7.1",
  "filament_id": null,
  "setting_id": null,
  "renamed_from": null,
  "filament_type": "PETG",
  "native_id": "IMADE3D.JellyBOX.2.N0.4:filament:1",
  "context": {
    "printer_model": "IMADE3D JellyBOX 2 N0 4"
  },
  "setting_scopes": {},
  "settings": {
    "outputTemp": {
      "4.7.1": 235
    },
    "outputBedTemp": {
      "4.7.1": 70
    },
    "type": {
      "4.7.1": "filament"
    },
    "name": {
      "4.7.1": "JB2 PETG - N0.4 L0.3 T235"
    },
    "filament_type": {
      "4.7.1": "PETG"
    },
    "compatible_printers": {
      "4.7.1": [
        "IMADE3D JellyBOX 2 N0 4 0.4 nozzle"
      ]
    }
  }
}