{
  "slicer": "cura",
  "profile_type": "filament",
  "name": "Color Inkjet PLA",
  "vendor": "XYZprinting",
  "first_seen": "5.13.0",
  "last_seen": "5.13.0",
  "filament_id": "a2b4e314-02f3-44fc-847e-e695b98304e9",
  "setting_id": "xyzprinting_colorinkjet_pla",
  "renamed_from": null,
  "filament_type": "PLA",
  "native_id": "xyzprinting_colorinkjet_pla",
  "context": {
    "native_id": "xyzprinting_colorinkjet_pla",
    "source_kind": "material",
    "resource_version": "5.13.0",
    "guid": "a2b4e314-02f3-44fc-847e-e695b98304e9",
    "brand": "XYZprinting",
    "material_type": "PLA",
    "color": "White",
    "color_code": "#ffffff",
    "description": "3D Color-inkjet PLA is the filament designed for da Vinci Color to bring full color to your 3D-printed models.",
    "diameter": 1.75,
    "machine_overrides": [],
    "compatibility": {
      "default": true,
      "machines": []
    }
  },
  "setting_scopes": {
    "material_guid": "extruder.0",
    "default_material_print_temperature": "extruder.0",
    "material_type": "extruder.0",
    "material_standby_temperature": "extruder.0",
    "material_diameter": "extruder.0",
    "material_brand": "extruder.0",
    "cool_fan_speed": "extruder.0",
    "default_material_bed_temperature": "global"
  },
  "settings": {
    "material_guid": {
      "5.13.0": "a2b4e314-02f3-44fc-847e-e695b98304e9"
    },
    "default_material_print_temperature": {
      "5.13.0": 210.0
    },
    "material_type": {
      "5.13.0": "PLA"
    },
    "material_standby_temperature": {
      "5.13.0": 210
    },
    "material_diameter": {
      "5.13.0": 1.75
    },
    "material_brand": {
      "5.13.0": "XYZprinting"
    },
    "cool_fan_speed": {
      "5.13.0": 100.0
    },
    "default_material_bed_temperature": {
      "5.13.0": 45
    }
  }
}