{
  "slicer": "cura",
  "profile_type": "filament",
  "name": "eMotionTech Acetate Generic",
  "vendor": "eMotionTech",
  "first_seen": "5.13.0",
  "last_seen": "5.13.0",
  "filament_id": "3ae65b77-96f2-4a9e-a949-5b24e29a09b2",
  "setting_id": "emotiontech_acetate",
  "renamed_from": null,
  "filament_type": "Acetate",
  "native_id": "emotiontech_acetate",
  "context": {
    "native_id": "emotiontech_acetate",
    "source_kind": "material",
    "resource_version": "5.13.0",
    "guid": "3ae65b77-96f2-4a9e-a949-5b24e29a09b2",
    "brand": "eMotionTech",
    "material_type": "Acetate",
    "color": "Generic",
    "color_code": "#D5D8DC",
    "description": "The Acetate 3D filament is recognized for its biodegradable properties and its natural UV resistance. In addition, it is a material that behaves very well against chemical agents such as chlorine, which makes it a real asset in the printing of 3D parts intended for optics or intended to be in contact with the skin.",
    "diameter": 1.75,
    "machine_overrides": [
      {
        "manufacturer": "eMotionTech",
        "product": "DUAL600",
        "identifiers": [
          {
            "manufacturer": "eMotionTech",
            "product": "DUAL600"
          }
        ],
        "compatible": true,
        "settings": {},
        "hotends": [
          {
            "id": "Standard 0.4",
            "compatible": true,
            "settings": {
              "default_material_print_temperature": 225,
              "retraction_amount": 2
            }
          },
          {
            "id": "Standard 0.6",
            "compatible": true,
            "settings": {
              "default_material_print_temperature": 233,
              "retraction_amount": 2
            }
          },
          {
            "id": "Standard 0.8",
            "compatible": false,
            "settings": {
              "default_material_print_temperature": 235,
              "retraction_amount": 2.3
            }
          },
          {
            "id": "Standard 1.0 Experimental",
            "compatible": false,
            "settings": {
              "default_material_print_temperature": 240,
              "retraction_amount": 2.5
            }
          },
          {
            "id": "Standard 1.2 Experimental",
            "compatible": false,
            "settings": {
              "default_material_print_temperature": 245,
              "retraction_amount": 2.7
            }
          },
          {
            "id": "High temp 0.4",
            "compatible": true,
            "settings": {
              "default_material_print_temperature": 225,
              "retraction_amount": 2
            }
          }
        ]
      },
      {
        "manufacturer": "eMotionTech",
        "product": "IDEX420",
        "identifiers": [
          {
            "manufacturer": "eMotionTech",
            "product": "IDEX420"
          },
          {
            "manufacturer": "eMotionTech",
            "product": "IDEX420 Duplicate"
          },
          {
            "manufacturer": "eMotionTech",
            "product": "IDEX420 Mirror"
          }
        ],
        "compatible": true,
        "settings": {},
        "hotends": [
          {
            "id": "IDEX420 Laiton 0.4",
            "compatible": true,
            "settings": {
              "default_material_print_temperature": 235
            }
          },
          {
            "id": "IDEX420 Laiton 0.6",
            "compatible": true,
            "settings": {
              "default_material_print_temperature": 235
            }
          },
          {
            "id": "IDEX420 Laiton 0.8",
            "compatible": false,
            "settings": {}
          },
          {
            "id": "IDEX420 Acier Durci 0.4",
            "compatible": false,
            "settings": {}
          }
        ]
      }
    ],
    "compatibility": {
      "default": true,
      "machines": [
        {
          "identifiers": [
            {
              "manufacturer": "eMotionTech",
              "product": "DUAL600"
            }
          ],
          "compatible": true,
          "hotends": {
            "Standard 0.4": true,
            "Standard 0.6": true,
            "Standard 0.8": false,
            "Standard 1.0 Experimental": false,
            "Standard 1.2 Experimental": false,
            "High temp 0.4": true
          }
        },
        {
          "identifiers": [
            {
              "manufacturer": "eMotionTech",
              "product": "IDEX420"
            },
            {
              "manufacturer": "eMotionTech",
              "product": "IDEX420 Duplicate"
            },
            {
              "manufacturer": "eMotionTech",
              "product": "IDEX420 Mirror"
            }
          ],
          "compatible": true,
          "hotends": {
            "IDEX420 Laiton 0.4": true,
            "IDEX420 Laiton 0.6": true,
            "IDEX420 Laiton 0.8": false,
            "IDEX420 Acier Durci 0.4": false
          }
        }
      ]
    }
  },
  "setting_scopes": {
    "material_guid": "extruder.0",
    "default_material_print_temperature": "extruder.0",
    "material_type": "extruder.0",
    "retraction_amount": "extruder.0",
    "material_standby_temperature": "extruder.0",
    "material_diameter": "extruder.0",
    "build_volume_temperature": "global",
    "material_brand": "extruder.0",
    "default_material_bed_temperature": "global"
  },
  "settings": {
    "material_guid": {
      "5.13.0": "3ae65b77-96f2-4a9e-a949-5b24e29a09b2"
    },
    "default_material_print_temperature": {
      "5.13.0": 235
    },
    "material_type": {
      "5.13.0": "Acetate"
    },
    "retraction_amount": {
      "5.13.0": 2
    },
    "material_standby_temperature": {
      "5.13.0": 100
    },
    "material_diameter": {
      "5.13.0": 1.75
    },
    "build_volume_temperature": {
      "5.13.0": 0
    },
    "material_brand": {
      "5.13.0": "eMotionTech"
    },
    "default_material_bed_temperature": {
      "5.13.0": 65
    }
  }
}